Workbook
Name IQ_CH: 110000
Name IQ_CQ: 5000
Name IQ_CY: 10000
Name IQ_DAILY: 500000
Name IQ_FH: 100000
Name IQ_FQ: 500
Name IQ_FY: 1000
Name IQ_LTM: 2000
Name IQ_MONTH: 15000
Name IQ_NTM: 6000
Name IQ_WEEK: 50000
Name IQ_YTD: 3000

Sheet Cover
C11: Valuation Modeling | M11: Strictly Confidential
C13: Table of Contents | H13: Model Checks
C15: Income Statement | H15: Incorrect Date Set for Valuation? | M15: =Inputs!$F$102 -> 0
C16: Balance Sheet | H16: Incorrect Date Set for First Cash Flow? | M16: =Inputs!$F$102 -> 0
C17: Cashflow Statement | H17: Terminal Growth Rate Greater Than or Equal To WACC? | M17: =Inputs!$F$112 -> 0
C18: Outputs | H18: Unused Tax Losses Remaining? (Levered Schedule) | M18: =Model!$D$189 -> 0
C19: Inputs | H19: Unused Tax Losses Remaining? (Unlevered Schedule) | M19: =Model!$D$226 -> 0
C20: Model | H20: Two UFCF Methods Different? | M20: =IF(SUM(Model!$I$286:$N$286)>0,1,0) -> 0
C21: PBI - Export
C33: © 2015 to 2024 CFI Education Inc.
C34: This Excel model is for educational purposes only and should not be used for any other reason. All content is Copyright material of CFI Education Inc.
C35: All rights reserved. The contents of this publication, including but not limited to all written material, content layout, images, formulas, and code, are protected
C36: under international copyright and trademark laws. No part of this publication may be modified, manipulated, reproduced, distributed, or transmitted in any
C37: form by any means, including photocopying, recording, or other electronic or mechanical methods, without prior written permission of the publisher,
C38: except in the case of certain noncommercial uses permitted by copyright law.
C40: https://corporatefinanceinstitute.com/

Sheet Income Statement
C1: NVIDIA CORPORATION (NASDAQGS:NVDA)
B3: Income Statement
H4: LTM
B5: For the Fiscal Period Ending | C5: 44227 | D5: 44591 | E5: 44955 | F5: 45319 | G5: 45683 | H5: 45684
B6: Period | C6: 12 months | D6: 12 months | E6: 12 months | F6: 12 months | G6: 12 months
B7: Currency | C7: USD | D7: USD | E7: USD | F7: USD | G7: USD | H7: USD
B9: Revenue | C9: 16675 | D9: 26914 | E9: 26974 | F9: 60922 | G9: 130497 | H9: 165218
B10: Other Revenue | C10: - | D10: - | E10: - | F10: - | G10: - | H10: -
B11: Total Revenue | C11: 16675 | D11: 26914 | E11: 26974 | F11: 60922 | G11: 130497 | H11: 165218
B13: Cost Of Goods Sold | C13: 6118 | D13: 9439 | E13: 11618 | F13: 16621 | G13: 32639 | H13: 49818
B14: Gross Profit | C14: 10557 | D14: 17475 | E14: 15356 | F14: 44301 | G14: 97858 | H14: 115400
B16: Selling General & Admin Exp. | C16: 1912 | D16: 2166 | E16: 2440 | F16: 2654 | G16: 3491 | H16: 4036
B17: R & D Exp. | C17: 3924 | D17: 5268 | E17: 7339 | F17: 8675 | G17: 12914 | H17: 15384
B18: Depreciation & Amort. | C18: - | D18: - | E18: - | F18: - | G18: - | H18: -
B19: Other Operating Expense/(Income) | C19: - | D19: - | E19: - | F19: - | G19: - | H19: -
B21: Other Operating Exp., Total | C21: 5836 | D21: 7434 | E21: 9779 | F21: 11329 | G21: 16405 | H21: 19420
B23: Operating Income | C23: 4721 | D23: 10041 | E23: 5577 | F23: 32972 | G23: 81453 | H23: 95980
B25: Interest Expense | C25: -184 | D25: -236 | E25: -262 | F25: -257 | G25: -247 | H25: -246
B26: Interest and Invest. Income | C26: 57 | D26: 29 | E26: 267 | F26: 866 | G26: 1786 | H26: 2091
B27: Net Interest Exp. | C27: -127 | D27: -207 | E27: 5 | F27: 609 | G27: 1539 | H27: 1845
B29: Currency Exchange Gains (Loss) | C29: - | D29: - | E29: - | F29: - | G29: - | H29: -
B30: Other Non-Operating Inc. (Exp.) | C30: 4 | D30: 7 | E30: -3 | F30: -1 | G30: 4 | H30: -14
B31: EBT Excl. Unusual Items | C31: 4598 | D31: 9841 | E31: 5579 | F31: 33580 | G31: 82996 | H31: 97811
B33: Restructuring Charges | C33: - | D33: - | E33: - | F33: - | G33: - | H33: -
B34: Merger & Related Restruct. Charges | C34: -189 | D34: - | E34: -1353 | F34: - | G34: - | H34: -
B35: Impairment of Goodwill | C35: - | D35: - | E35: - | F35: - | G35: - | H35: -
B36: Gain (Loss) On Sale Of Invest. | C36: - | D36: 100 | E36: -45 | F36: 238 | G36: 1030 | H36: 2839
B37: Other Unusual Items | C37: - | D37: - | E37: - | F37: - | G37: - | H37: -
B38: EBT Incl. Unusual Items | C38: 4409 | D38: 9941 | E38: 4181 | F38: 33818 | G38: 84026 | H38: 100650
B40: Income Tax Expense | C40: 77 | D40: 189 | E40: -187 | F40: 4058 | G40: 11146 | H40: 14053
B41: Earnings from Cont. Ops. | C41: 4332 | D41: 9752 | E41: 4368 | F41: 29760 | G41: 72880 | H41: 86597
B43: Earnings of Discontinued Ops. | C43: - | D43: - | E43: - | F43: - | G43: - | H43: -
B44: Extraord. Item & Account. Change | C44: - | D44: - | E44: - | F44: - | G44: - | H44: -
B45: Net Income to Company | C45: 4332 | D45: 9752 | E45: 4368 | F45: 29760 | G45: 72880 | H45: 86597
B47: Minority Int. in Earnings | C47: - | D47: - | E47: - | F47: - | G47: - | H47: -
B48: Net Income | C48: 4332 | D48: 9752 | E48: 4368 | F48: 29760 | G48: 72880 | H48: 86597
B50: Pref. Dividends and Other Adj. | C50: - | D50: - | E50: - | F50: - | G50: - | H50: -
B52: NI to Common Incl Extra Items | C52: 4332 | D52: 9752 | E52: 4368 | F52: 29760 | G52: 72880 | H52: 86597
B53: NI to Common Excl. Extra Items | C53: 4332 | D53: 9752 | E53: 4368 | F53: 29760 | G53: 72880 | H53: 86597
B55: Per Share Items
B56: Basic EPS | C56: 0.18 | D56: 0.39 | E56: 0.18 | F56: 1.21 | G56: 2.97 | H56: 3.54
B57: Basic EPS Excl. Extra Items | C57: 0.175597 | D57: 0.390705 | E57: 0.175633 | F57: 1.205346 | G57: 2.96803 | H57: 3.540713
B58: Weighted Avg. Basic Shares Out. | C58: 24670 | D58: 24960 | E58: 24870 | F58: 24690 | G58: 24555 | H58: 24457.5
B60: Diluted EPS | C60: 0.17 | D60: 0.39 | E60: 0.17 | F60: 1.19 | G60: 2.94 | H60: 3.51
B61: Diluted EPS Excl. Extra Items | C61: 0.173 | D61: 0.385 | E61: 0.17 | F61: 1.19 | G61: 2.94 | H61: 3.510475
B62: Weighted Avg. Diluted Shares Out. | C62: 25100 | D62: 25350 | E62: 25070 | F62: 24940 | G62: 24804 | H62: 24655
B64: Normalized Basic EPS | C64: 0.12 | D64: 0.25 | E64: 0.14 | F64: 0.85 | G64: 2.11 | H64: 2.5
B65: Normalized Diluted EPS | C65: 0.114492 | D65: 0.242628 | E65: 0.139085 | F65: 0.841519 | G65: 2.091295 | H65: 2.479491
B67: Dividends per Share | C67: 0.02 | D67: 0.02 | E67: 0.02 | F67: 0.02 | G67: 0.03 | H67: 0.04
B68: Payout Ratio % | C68: 0.091181 | D68: 0.040914 | E68: 0.091117 | F68: 0.013272 | G68: 0.011443 | H68: 0.011293
B70: Shares per Depository Receipt | C70: 0.17174 | D70: 0.17174 | E70: 0.17174 | F70: 0.17174 | G70: 0.17174 | H70: 0.17174
B72: Supplemental Items
B73: EBITDA | C73: 5819 | D73: 11215 | E73: 7121 | F73: 34480 | G73: 83317 | H73: 98281
B74: EBITA | C74: 5333 | D74: 10604 | E74: 6276 | F74: 33586 | G74: 82046 | H74: 96527
B75: EBIT | C75: 4721 | D75: 10041 | E75: 5577 | F75: 32972 | G75: 81453 | H75: 95980
B76: EBITDAR | C76: 5964 | D76: 11383 | E76: 7314 | F76: 34749 | G76: 83673 | H76: NA
B77: Effective Tax Rate % | C77: 0.017464 | D77: 0.019012 | E77: NM | F77: 0.119995 | G77: 0.132649 | H77: 0.139622
B78: Current Domestic Taxes | C78: 198 | D78: 524 | E78: 1749 | F78: 6045 | G78: 14924 | H78: 14924
B79: Current Foreign Taxes | C79: 161 | D79: 71 | E79: 228 | F79: 502 | G79: 699 | H79: 699
B80: Total Current Taxes | C80: 359 | D80: 595 | E80: 1977 | F80: 6547 | G80: 15623 | H80: 15623
B81: Deferred Domestic Taxes | C81: -246 | D81: -420 | E81: -2165 | F81: -2705 | G81: -4757 | H81: -4757
B82: Deferred Foreign Taxes | C82: -36 | D82: 14 | E82: 1 | F82: 216 | G82: 280 | H82: 280
B83: Total Deferred Taxes | C83: -282 | D83: -406 | E83: -2164 | F83: -2489 | G83: -4477 | H83: -4477
B85: Normalized Net Income | C85: 2873.75 | D85: 6150.625 | E85: 3486.875 | F85: 20987.5 | G85: 51872.5 | H85: 61131.875
B86: Interest on Long Term Debt | C86: NA | D86: NA | E86: NA | F86: NA | G86: NA | H86: NA
B87: Filing Date | C87: 44981 | D87: 45343 | E87: 45714 | F87: 45714 | G87: 45714 | H87: 45896
B88: Restatement Type | C88: NC | D88: NC | E88: NC | F88: NC | G88: O | H88: O
B89: Calculation Type | C89: REP | D89: REP | E89: REP | F89: REP | G89: REP | H89: LTM
B91: Supplemental Operating Expense Items
B92: Advertising Exp. | C92: NA | D92: NA | E92: NA | F92: NA | G92: NA | H92: NA
B93: Selling and Marketing Exp. | C93: NA | D93: NA | E93: NA | F93: NA | G93: NA | H93: NA
B94: R&D Exp. | C94: 3924 | D94: 5268 | E94: 7339 | F94: 8675 | G94: 12914 | H94: 15384
B95: Net Rental Exp. | C95: 145 | D95: 168 | E95: 193 | F95: 269 | G95: 356 | H95: NA
B96: Imputed Oper. Lease Interest Exp. | C96: 41.68692 | D96: 32.651136 | E96: 33.904696 | F96: 47.909976 | G96: 65.971072 | H96: -
B97: Imputed Oper. Lease Depreciation | C97: 103.31308 | D97: 135.34886 | E97: 159.0953 | F97: 221.09002 | G97: 290.02893 | H97: -
B99: Stock-Based Comp., COGS | C99: 88 | D99: 141 | E99: 138 | F99: 141 | G99: 178 | H99: 226
B100: Stock-Based Comp., R&D Exp. | C100: 860 | D100: 1298 | E100: 1892 | F100: 2532 | G100: 3423 | H100: 4118
B101: Stock-Based Comp., SG&A Exp. | C101: 449 | D101: 565 | E101: 680 | F101: 876 | G101: 1136 | H101: 1328
B102: Stock-Based Comp., Total | C102: 1397 | D102: 2004 | E102: 2710 | F102: 3549 | G102: 4737 | H102: 5672
B105: Note: For multiple class companies, per share items are primary class equivalent, and for foreign companies listed as primary ADRs, per share items are ADR-equivalent.
B106: Data items have been saved at different times with multiple currencies. Values are converted where necessary to the most common currency of the filing.
B107: Source: S&P Capital IQ

Sheet Balance Sheet
C1: NVIDIA CORPORATION (NASDAQGS:NVDA)
B3: Balance Sheet
H4: LTM
B5: For the Fiscal Period Ending | C5: 44227 | D5: 44591 | E5: 44955 | F5: 45319 | G5: 45683 | H5: 45684
B6: Period | C6: 12 months | D6: 12 months | E6: 12 months | F6: 12 months | G6: 12 months
B7: Currency | C7: USD | D7: USD | E7: USD | F7: USD | G7: USD | H7: USD
B8: ASSETS
B9: Cash And Equivalents | C9: 847 | D9: 1990 | E9: 3389 | F9: 7280 | G9: 8589 | H9: 11639
B10: Short Term Investments | C10: 10714 | D10: 19218 | E10: 9907 | F10: 18704 | G10: 34621 | H10: 45152
B11: Total Cash & ST Investments | C11: 11561 | D11: 21208 | E11: 13296 | F11: 25984 | G11: 43210 | H11: 56791
B13: Accounts Receivable | C13: 2429 | D13: 4650 | E13: 3827 | F13: 9999 | G13: 23065 | H13: 27808
B14: Total Receivables | C14: 2429 | D14: 4650 | E14: 3827 | F14: 9999 | G14: 23065 | H14: 27808
B16: Inventory | C16: 1826 | D16: 2605 | E16: 5159 | F16: 5282 | G16: 10080 | H16: 14962
B17: Prepaid Exp. | C17: 239 | D17: 366 | E17: 791 | F17: 3080 | G17: 3771 | H17: 858
B18: Deferred Tax Assets, Curr. | C18: - | D18: - | E18: - | F18: - | G18: - | H18: -
B19: Other Current Assets | C19: - | D19: - | E19: - | F19: - | G19: - | H19: 1800
B20: Total Current Assets | C20: 16055 | D20: 28829 | E20: 23073 | F20: 44345 | G20: 80126 | H20: 102219
B22: Gross Property, Plant & Equipment | C22: 4264 | D22: 5510 | E22: 7539 | F22: 8769 | G22: 12477 | H22: -
B23: Accumulated Depreciation | C23: -1408 | D23: -1903 | E23: -2694 | F23: -3509 | G23: -4401 | H23: -
B24: Net Property, Plant & Equipment | C24: 2856 | D24: 3607 | E24: 4845 | F24: 5260 | G24: 8076 | H24: 11225
B26: Long-term Investments | C26: 144 | D26: 266 | E26: 299 | F26: 1321 | G26: 3387 | H26: 3799
B27: Goodwill | C27: 4193 | D27: 4349 | E27: 4372 | F27: 4430 | G27: 5188 | H27: 5755
B28: Other Intangibles | C28: 2737 | D28: 2339 | E28: 1676 | F28: 1112 | G28: 807 | H28: 755
B29: Deferred Tax Assets, LT | C29: 806 | D29: 1222 | E29: 3396 | F29: 6081 | G29: 10979 | H29: 13570
B30: Other Long-Term Assets | C30: 2000 | D30: 3575 | E30: 3521 | F30: 3179 | G30: 3038 | H30: 3417
B31: Total Assets | C31: 28791 | D31: 44187 | E31: 41182 | F31: 65728 | G31: 111601 | H31: 140740
B33: LIABILITIES
B34: Accounts Payable | C34: 1149 | D34: 1783 | E34: 1193 | F34: 2699 | G34: 6310 | H34: 9064
B35: Accrued Exp. | C35: 297 | D35: 409 | E35: 530 | F35: 675 | G35: 848 | H35: 4381
B36: Curr. Port. of LT Debt | C36: 999 | D36: - | E36: 1250 | F36: 1250 | G36: - | H36: -
B37: Curr. Port. of Leases | C37: - | D37: 144 | E37: 176 | F37: 228 | G37: 288 | H37: 301
B38: Curr. Income Taxes Payable | C38: - | D38: 132 | E38: 467 | F38: 296 | G38: 881 | H38: 1910
B39: Unearned Revenue, Current | C39: 288 | D39: 300 | E39: 354 | F39: 764 | G39: 837 | H39: 980
B40: Other Current Liabilities | C40: 1192 | D40: 1567 | E40: 2593 | F40: 4719 | G40: 8883 | H40: 7621
B41: Total Current Liabilities | C41: 3925 | D41: 4335 | E41: 6563 | F41: 10631 | G41: 18047 | H41: 24257
B43: Long-Term Debt | C43: 5964 | D43: 10946 | E43: 9703 | F43: 8459 | G43: 8463 | H43: 8466
B44: Long-Term Leases | C44: 634 | D44: 741 | E44: 902 | F44: 1119 | G44: 1519 | H44: 1831
B45: Unearned Revenue, Non-Current | C45: 163 | D45: 202 | E45: 218 | F45: 573 | G45: 976 | H45: 1055
B46: Pension & Other Post-Retire. Benefits | C46: - | D46: - | E46: - | F46: - | G46: - | H46: -
B47: Def. Tax Liability, Non-Curr. | C47: 241 | D47: 245 | E47: 247 | F47: 462 | G47: 886 | H47: 1351
B48: Other Non-Current Liabilities | C48: 971 | D48: 1106 | E48: 1448 | F48: 1506 | G48: 2383 | H48: 3649
B49: Total Liabilities | C49: 11898 | D49: 17575 | E49: 19081 | F49: 22750 | G49: 32274 | H49: 40609
B51: Common Stock | C51: 3 | D51: 3 | E51: 2 | F51: 25 | G51: 24 | H51: 24
B52: Additional Paid In Capital | C52: 8719 | D52: 10385 | E52: 11971 | F52: 13109 | G52: 11237 | H52: 11200
B53: Retained Earnings | C53: 18908 | D53: 16235 | E53: 10171 | F53: 29817 | G53: 68038 | H53: 88737
B54: Treasury Stock | C54: -10756 | D54: - | E54: - | F54: - | G54: - | H54: -
B55: Comprehensive Inc. and Other | C55: 19 | D55: -11 | E55: -43 | F55: 27 | G55: 28 | H55: 170
B56: Total Common Equity | C56: 16893 | D56: 26612 | E56: 22101 | F56: 42978 | G56: 79327 | H56: 100131
B58: Total Equity | C58: 16893 | D58: 26612 | E58: 22101 | F58: 42978 | G58: 79327 | H58: 100131
B60: Total Liabilities And Equity | C60: 28791 | D60: 44187 | E60: 41182 | F60: 65728 | G60: 111601 | H60: 140740
B62: Supplemental Items
B63: Total Shares Out. on Filing Date | C63: 24800 | D63: 25060 | E63: 24700 | F63: 25000 | G63: 24400 | H63: 24300
B64: Total Shares Out. on Balance Sheet Date | C64: 24800 | D64: 25060 | E64: 24660 | F64: 24640 | G64: 24477 | H64: 24347
B65: Book Value/Share | C65: 0.68 | D65: 1.06 | E65: 0.9 | F65: 1.74 | G65: 3.24 | H65: 4.11
B66: Tangible Book Value | C66: 9963 | D66: 19924 | E66: 16053 | F66: 37436 | G66: 73332 | H66: 93621
B67: Tangible Book Value/Share | C67: 0.4 | D67: 0.8 | E67: 0.65 | F67: 1.52 | G67: 3 | H67: 3.85
B68: Total Debt | C68: 7597 | D68: 11831 | E68: 12031 | F68: 11056 | G68: 10270 | H68: 10598
B69: Net Debt | C69: -3964 | D69: -9377 | E69: -1265 | F69: -14928 | G69: -32940 | H69: -46193
B70: Debt Equivalent Oper. Leases | C70: 1160 | D70: 1344 | E70: 1544 | F70: 2152 | G70: 2848 | H70: NA
B71: Inventory Method | C71: NA | D71: NA | E71: NA | F71: NA | G71: NA | H71: NA
B72: Raw Materials Inventory | C72: 632 | D72: 791 | E72: 2430 | F72: 1719 | G72: 3408 | H72: 1843
B73: Work in Progress Inventory | C73: 457 | D73: 692 | E73: 466 | F73: 1505 | G73: 3399 | H73: 4411
B74: Finished Goods Inventory | C74: 737 | D74: 1122 | E74: 2263 | F74: 2058 | G74: 3273 | H74: 8708
B75: Land | C75: 218 | D75: 218 | E75: 218 | F75: 218 | G75: 511 | H75: NA
B76: Buildings | C76: 796 | D76: 874 | E76: 1598 | F76: 1816 | G76: 2076 | H76: NA
B77: Machinery | C77: 1985 | D77: 2852 | E77: 4303 | F77: 5200 | G77: 7568 | H77: NA
B78: Construction in Progress | C78: 558 | D78: 737 | E78: 382 | F78: 189 | G78: 529 | H78: -
B79: Leasehold Improvements | C79: - | D79: - | E79: - | F79: - | G79: - | H79: -
B80: Full Time Employees | C80: 18975 | D80: 22473 | E80: 26196 | F80: 29600 | G80: 36000 | H80: NA
B81: Assets under Cap. Lease, Gross | C81: NA | D81: NA | E81: NA | F81: NA | G81: NA | H81: NA
B82: Accum. Allowance for Doubtful Accts | C82: 4 | D82: 4 | E82: 4 | F82: 4 | G82: 4 | H82: NA
B83: Filing Date | C83: 44981 | D83: 45343 | E83: 45714 | F83: 45714 | G83: 45714 | H83: 45896
B84: Restatement Type | C84: NC | D84: NC | E84: NC | F84: NC | G84: O | H84: O
B85: Calculation Type | C85: RUP | D85: RUP | E85: RUP | F85: REP | G85: REP | H85: REP
B88: Note: For multiple class companies, total share counts are primary class equivalent, and for foreign companies listed as primary ADRs, total share counts are ADR-equivalent.
B89: Data items have been saved at different times with multiple currencies. Values are converted where necessary to the most common currency of the filing.
B90: Source: S&P Capital IQ

Sheet Cashflow Statement
C1: NVIDIA CORPORATION (NASDAQGS:NVDA)
B3: Cash Flow
H4: LTM
B5: For the Fiscal Period Ending | C5: 44227 | D5: 44591 | E5: 44955 | F5: 45319 | G5: 45683 | H5: 45684
B6: Period | C6: 12 months | D6: 12 months | E6: 12 months | F6: 12 months | G6: 12 months
B7: Currency | C7: USD | D7: USD | E7: USD | F7: USD | G7: USD | H7: USD
B9: Net Income | C9: 4332 | D9: 9752 | E9: 4368 | F9: 29760 | G9: 72880 | H9: 86597
B10: Depreciation & Amort. | C10: 486 | D10: 611 | E10: 845 | F10: 894 | G10: 1271 | H10: 1754
B11: Amort. of Goodwill and Intangibles | C11: 612 | D11: 563 | E11: 699 | F11: 614 | G11: 593 | H11: 547
B12: Depreciation & Amort., Total | C12: 1098 | D12: 1174 | E12: 1544 | F12: 1508 | G12: 1864 | H12: 2301
B14: Other Amortization | C14: - | D14: - | E14: - | F14: - | G14: - | H14: -
B15: (Gain) Loss From Sale Of Assets | C15: - | D15: - | E15: - | F15: - | G15: - | H15: -
B16: (Gain) Loss On Sale Of Invest. | C16: - | D16: -100 | E16: 45 | F16: -238 | G16: -1030 | H16: -2839
B17: Asset Writedown & Restructuring Costs | C17: - | D17: - | E17: - | F17: - | G17: - | H17: -
B18: Stock-Based Compensation | C18: 1397 | D18: 2004 | E18: 2709 | F18: 3549 | G18: 4737 | H18: 5672
B19: Tax Benefit from Stock Options | C19: - | D19: - | E19: - | F19: - | G19: - | H19: -
B20: Other Operating Activities | C20: -302 | D20: -359 | E20: -818 | F20: -2767 | G20: -4979 | H20: -3771
B21: Change in Acc. Receivable | C21: -550 | D21: -2215 | E21: 822 | F21: -6172 | G21: -13063 | H21: -13673
B22: Change In Inventories | C22: -524 | D22: -774 | E22: -2554 | F22: -98 | G22: -4781 | H22: -8281
B23: Change in Acc. Payable | C23: 312 | D23: 568 | E23: -551 | F23: 1531 | G23: 3357 | H23: 4811
B24: Change in Other Net Operating Assets | C24: 59 | D24: -942 | E24: 76 | F24: 1017 | G24: 5104 | H24: 6218
B25: Cash from Ops. | C25: 5822 | D25: 9108 | E25: 5641 | F25: 28090 | G25: 64089 | H25: 77035
B27: Capital Expenditure | C27: -1128 | D27: -976 | E27: -1833 | F27: -1069 | G27: -3236 | H27: -5012
B28: Sale of Property, Plant, and Equipment | C28: - | D28: - | E28: - | F28: - | G28: - | H28: -
B29: Cash Acquisitions | C29: -8524 | D29: -263 | E29: -49 | F29: -83 | G29: -1007 | H29: -1367
B30: Divestitures | C30: - | D30: - | E30: - | F30: - | G30: - | H30: -
B31: Invest. in Marketable & Equity Securt. | C31: -10023 | D31: -8591 | E31: 9257 | F31: -9290 | G31: -16200 | H31: -17530
B32: Net (Inc.) Dec. in Loans Originated/Sold | C32: - | D32: - | E32: - | F32: - | G32: - | H32: -
B33: Other Investing Activities | C33: - | D33: - | E33: - | F33: -124 | G33: 22 | H33: 22
B34: Cash from Investing | C34: -19675 | D34: -9830 | E34: 7375 | F34: -10566 | G34: -20421 | H34: -23887
B36: Short Term Debt Issued | C36: - | D36: - | E36: - | F36: - | G36: - | H36: -
B37: Long-Term Debt Issued | C37: 4968 | D37: 4977 | E37: - | F37: - | G37: - | H37: -
B38: Total Debt Issued | C38: 4968 | D38: 4977 | E38: - | F38: - | G38: - | H38: -
B39: Short Term Debt Repaid | C39: - | D39: - | E39: - | F39: - | G39: - | H39: -
B40: Long-Term Debt Repaid | C40: - | D40: -1000 | E40: - | F40: -1250 | G40: -1250 | H40: -
B41: Total Debt Repaid | C41: - | D41: -1000 | E41: - | F41: -1250 | G41: -1250 | H41: 0
B43: Issuance of Common Stock | C43: 194 | D43: 281 | E43: 355 | F43: 403 | G43: 490 | H43: 575
B44: Repurchase of Common Stock | C44: -942 | D44: -1904 | E44: -11514 | F44: -12316 | G44: -40636 | H44: -49544
B46: Common Dividends Paid | C46: -395 | D46: -399 | E46: -398 | F46: -395 | G46: -834 | H46: -978
B47: Total Dividends Paid | C47: -395 | D47: -399 | E47: -398 | F47: -395 | G47: -834 | H47: -978
B49: Special Dividend Paid | C49: - | D49: - | E49: - | F49: - | G49: - | H49: -
B50: Other Financing Activities | C50: -21 | D50: -90 | E50: -60 | F50: -75 | G50: -129 | H50: -133
B51: Cash from Financing | C51: 3804 | D51: 1865 | E51: -11617 | F51: -13633 | G51: -42359 | H51: -50080
B53: Net Change in Cash | C53: -10049 | D53: 1143 | E53: 1399 | F53: 3891 | G53: 1309 | H53: 3068
B55: Supplemental Items
B56: Cash Interest Paid | C56: 138 | D56: 246 | E56: 254 | F56: 252 | G56: 246 | H56: 246
B57: Cash Taxes Paid | C57: 249 | D57: 396 | E57: 1404 | F57: 6549 | G57: 15118 | H57: 16120
B58: Levered Free Cash Flow | C58: 3734.625 | D58: 6468.125 | E58: 4532.875 | F58: 19866.875 | G58: 44169.75 | H58: 52436.75
B59: Unlevered Free Cash Flow | C59: 3849.625 | D59: 6615.625 | E59: 4696.625 | F59: 20027.5 | G59: 44324.125 | H59: 52590.5
B60: Change in Net Working Capital | C60: 468 | D60: 1862 | E60: 1210 | F60: 4568 | G60: 9949 | H60: 10358
B61: Net Debt Issued | C61: 4968 | D61: 3977 | E61: NA | F61: -1250 | G61: -1250 | H61: 0
B62: Filing Date | C62: 44981 | D62: 45343 | E62: 45714 | F62: 45714 | G62: 45714 | H62: 45896
B63: Restatement Type | C63: NC | D63: NC | E63: NC | F63: NC | G63: O | H63: O
B64: Calculation Type | C64: REP | D64: REP | E64: REP | F64: REP | G64: REP | H64: LTM
B66: Data items have been saved at different times with multiple currencies. Values are converted where necessary to the most common currency of the filing.
B67: Source: S&P Capital IQ

Sheet Outputs
F1: NVIDIA CORPORATION (NASDAQGS:NVDA)
B3: Dashboard: Perpetuity Method
D5: Model Drivers Set To | F5: 2 | L5: All figures in USD thousands unless stated
D7: Main Outputs | L7: Selected Inputs
F9: Enterprise | G9: Equity | H9: Equity
F10: Value | G10: Value | H10: Per Share | L10: Terminal Growth Rate | O10: =Inputs!F109 -> 0.03
F11: =Model!J323 -> 635353.15 | L11: WACC | O11: =Inputs!F111 -> 0.10320887
D12: Best Case | E12: 1 | F12: 646845.24 | G12: =F12-$O$12 -> 679785.24 | H12: =G12/$O$13 -> 279.74701 | L12: Net Debt | N12: =CONCATENATE("(End of ",2025,")") -> (End of 2025) | O12: ='Balance Sheet'!G69 -> -32940
D13: Base Case | E13: 2 | F13: 635353.15 | G13: =F13-$O$12 -> 668293.15 | H13: =G13/$O$13 -> 275.01776 | L13: Shares Outstanding | N13: (FD 000) | O13: =Inputs!F107 -> 2430
D14: Worst Case | E14: 3 | F14: 577042.43 | G14: =F14-$O$12 -> 609982.43 | H14: =G14/$O$13 -> 251.02158 | L14: Current Stock Price | N14: (US$/sh) | O14: =Inputs!F108 -> 176.67
D17: Enterprise Value | L17: Equity Value per Share
D19: Terminal Growth Rate | L19: Terminal Growth Rate
C20: =Model!J323 -> 635353.15 | D20: =E20-0.01 -> 0.01 | E20: =F20-0.01 -> 0.02 | F20: =Inputs!F109 -> 0.03 | G20: =F20+0.01 -> 0.04 | H20: =G20+0.01 -> 0.05 | L20: =D20 -> 0.01 | M20: =E20 -> 0.02 | N20: =F20 -> 0.03 | O20: =G20 -> 0.04 | P20: =H20 -> 0.05
B21: WACC | C21: =C22-0.01 -> 0.083208871 | D21: 686381.18 | E21: 780728.57 | F21: 910539 | G21: 1100434.5 | H21: 1404694.3 | J21: WACC | K21: =C21 -> 0.083208871 | L21: =D32/$O$13 -> 296.01695 | M21: =E32/$O$13 -> 334.84303 | N21: =F32/$O$13 -> 388.26296 | O21: =G32/$O$13 -> 466.40926 | P21: =H32/$O$13 -> 591.61907
C22: =C23-0.01 -> 0.093208871 | D22: 591398.35 | E22: 660249.21 | F22: 750885.26 | G22: 875589.34 | H22: 1058014.9 | K22: =C22 -> 0.093208871 | L22: =D33/$O$13 -> 256.92936 | M22: =E33/$O$13 -> 285.26305 | N22: =F33/$O$13 -> 322.56184 | O22: =G33/$O$13 -> 373.88038 | P22: =H33/$O$13 -> 448.95264
C23: =Inputs!F111 -> 0.10320887 | D23: 517217.35 | E23: 569186.5 | F23: 635353.15 | G23: 722455.68 | H23: 842298.06 | K23: =C23 -> 0.10320887 | L23: =D34/$O$13 -> 226.4022 | M23: =E34/$O$13 -> 247.78868 | N23: =F34/$O$13 -> 275.01776 | O23: =G34/$O$13 -> 310.86242 | P23: =H34/$O$13 -> 360.18027
C24: =C23+0.01 -> 0.11320887 | D24: 457773.5 | E24: 498052.98 | F24: 548014 | G24: 611623.91 | H24: 695360.71 | K24: =C24 -> 0.11320887 | L24: =D35/$O$13 -> 201.93971 | M24: =E35/$O$13 -> 218.51563 | N24: =F35/$O$13 -> 239.07572 | O24: =G35/$O$13 -> 265.25264 | P24: =H35/$O$13 -> 299.71223
C25: =C24+0.01 -> 0.12320887 | D25: 409145.9 | E25: 441039.19 | F25: 479775.88 | G25: 527823.28 | H25: 588996.8 | K25: =C25 -> 0.12320887 | L25: =D36/$O$13 -> 181.92835 | M25: =E36/$O$13 -> 195.05316 | N25: =F36/$O$13 -> 210.99419 | O25: =G36/$O$13 -> 230.76678 | P25: =H36/$O$13 -> 255.94107
D28: Equity Value | L28: Premium (Discount) to Stock Price
D30: Terminal Growth Rate | L30: Terminal Growth Rate
D31: =L20 -> 0.01 | E31: =M20 -> 0.02 | F31: =N20 -> 0.03 | G31: =O20 -> 0.04 | H31: =P20 -> 0.05 | L31: =D31 -> 0.01 | M31: =E31 -> 0.02 | N31: =F31 -> 0.03 | O31: =G31 -> 0.04 | P31: =H31 -> 0.05
B32: WACC | C32: =K21 -> 0.083208871 | D32: =D21-$O$12 -> 719321.18 | E32: =E21-$O$12 -> 813668.57 | F32: =F21-$O$12 -> 943479 | G32: =G21-$O$12 -> 1133374.5 | H32: =H21-$O$12 -> 1437634.3 | J32: WACC | K32: =C32 -> 0.083208871 | L32: =L21/$O$14-1 -> 0.67553601 | M32: =M21/$O$14-1 -> 0.89530217 | N32: =N21/$O$14-1 -> 1.1976734 | O32: =O21/$O$14-1 -> 1.6400026 | P32: =P21/$O$14-1 -> 2.348724
C33: =K22 -> 0.093208871 | D33: =D22-$O$12 -> 624338.35 | E33: =E22-$O$12 -> 693189.21 | F33: =F22-$O$12 -> 783825.26 | G33: =G22-$O$12 -> 908529.34 | H33: =H22-$O$12 -> 1090954.9 | K33: =C33 -> 0.093208871 | L33: =L22/$O$14-1 -> 0.4542897 | M33: =M22/$O$14-1 -> 0.61466604 | N33: =N22/$O$14-1 -> 0.82578726 | O33: =O22/$O$14-1 -> 1.1162641 | P33: =P22/$O$14-1 -> 1.5411934
C34: =K23 -> 0.10320887 | D34: =D23-$O$12 -> 550157.35 | E34: =E23-$O$12 -> 602126.5 | F34: =F23-$O$12 -> 668293.15 | G34: =G23-$O$12 -> 755395.68 | H34: =H23-$O$12 -> 875238.06 | K34: =C34 -> 0.10320887 | L34: =L23/$O$14-1 -> 0.28149772 | M34: =M23/$O$14-1 -> 0.40255099 | N34: =N23/$O$14-1 -> 0.55667493 | O34: =O23/$O$14-1 -> 0.75956541 | P34: =P23/$O$14-1 -> 1.0387178
C35: =K24 -> 0.11320887 | D35: =D24-$O$12 -> 490713.5 | E35: =E24-$O$12 -> 530992.98 | F35: =F24-$O$12 -> 580954 | G35: =G24-$O$12 -> 644563.91 | H35: =H24-$O$12 -> 728300.71 | K35: =C35 -> 0.11320887 | L35: =L24/$O$14-1 -> 0.14303341 | M35: =M24/$O$14-1 -> 0.23685759 | N35: =N24/$O$14-1 -> 0.35323325 | O35: =O24/$O$14-1 -> 0.50140169 | P35: =P24/$O$14-1 -> 0.6964523
C36: =K25 -> 0.12320887 | D36: =D25-$O$12 -> 442085.9 | E36: =E25-$O$12 -> 473979.19 | F36: =F25-$O$12 -> 512715.88 | G36: =G25-$O$12 -> 560763.28 | H36: =H25-$O$12 -> 621936.8 | K36: =C36 -> 0.12320887 | L36: =L25/$O$14-1 -> 0.029763696 | M36: =M25/$O$14-1 -> 0.10405367 | N36: =N25/$O$14-1 -> 0.19428419 | O36: =O25/$O$14-1 -> 0.30620242 | P36: =P25/$O$14-1 -> 0.4486957
B40: Dashboard: Exit Multiple Method
D42: Model Drivers Set To | L42: All figures in USD thousands unless stated
D44: Main Outputs | L44: Selected Inputs
F46: Enterprise | G46: Equity | H46: Equity
F47: Value | G47: Value | H47: Per Share | L47: Terminal Multiple | O47: =Inputs!F110 -> 16
F48: =Model!$J$368 -> 912518.6 | L48: WACC | O48: =Inputs!F111 -> 0.10320887
D49: =D12 -> Best Case | E49: 1 | F49: 962857.63 | G49: =F49-$O$49 -> 995797.63 | H49: =+G49/$O$50 -> 409.79326 | L49: Net Debt | N49: =N12 -> (End of 2025) | O49: ='Balance Sheet'!G69 -> -32940
D50: =D13 -> Base Case | E50: 2 | F50: 912518.6 | G50: =F50-$O$49 -> 945458.6 | H50: =+G50/$O$50 -> 389.07761 | L50: Shares Outstanding | N50: (FD 000) | O50: =Inputs!F107 -> 2430
D51: =D14 -> Worst Case | E51: 3 | F51: 790770.3 | G51: =F51-$O$49 -> 823710.3 | H51: =+G51/$O$50 -> 338.97543 | L51: Current Stock Price | N51: (US$/sh) | O51: =Inputs!F108 -> 176.67
D54: Enterprise Value | L54: Equity Value per Share
D56: Terminal Multiple | L56: Terminal Multiple
C57: =Model!J368 -> 912518.6 | D57: =E57-0.5 -> 15 | E57: =F57-0.5 -> 15.5 | F57: =Inputs!F110 -> 16 | G57: =+F57+0.5 -> 16.5 | H57: =+G57+0.5 -> 17 | L57: =D57 -> 15 | M57: =E57 -> 15.5 | N57: =F57 -> 16 | O57: =G57 -> 16.5 | P57: =H57 -> 17
B58: WACC | C58: =C59-0.01 -> 0.083208871 | D58: 948602.62 | E58: 975878.48 | F58: 1003154.3 | G58: 1030430.2 | H58: 1057706 | J58: WACC | K58: =C58 -> 0.083208871 | L58: =D69/$O$50 -> 403.92701 | M58: =E69/$O$50 -> 415.15164 | N58: =F69/$O$50 -> 426.37627 | O58: =G69/$O$50 -> 437.6009 | P58: =H69/$O$50 -> 448.82553
C59: =C60-0.01 -> 0.093208871 | D59: 904610.83 | E59: 930574.05 | F59: 956537.26 | G59: 982500.48 | H59: 1008463.7 | K59: =C59 -> 0.093208871 | L59: =D70/$O$50 -> 385.82339 | M59: =E70/$O$50 -> 396.50784 | N59: =F70/$O$50 -> 407.19229 | O59: =G70/$O$50 -> 417.87674 | P59: =H70/$O$50 -> 428.56119
C60: =Inputs!F111 -> 0.10320887 | D60: 863068.9 | E60: 887793.75 | F60: 912518.6 | G60: 937243.45 | H60: 961968.3 | K60: =C60 -> 0.10320887 | L60: =D71/$O$50 -> 368.72794 | M60: =E71/$O$50 -> 378.90278 | N60: =F71/$O$50 -> 389.07761 | O60: =G71/$O$50 -> 399.25245 | P60: =H71/$O$50 -> 409.42728
C61: =C60+0.01 -> 0.11320887 | D61: 823819.32 | E61: 847375.26 | F61: 870931.2 | G61: 894487.13 | H61: 918043.07 | K61: =C61 -> 0.11320887 | L61: =D72/$O$50 -> 352.57585 | M61: =E72/$O$50 -> 362.26965 | N61: =F72/$O$50 -> 371.96346 | O61: =G72/$O$50 -> 381.65726 | P61: =H72/$O$50 -> 391.35106
C62: =C61+0.01 -> 0.12320887 | D62: 786716.04 | E62: 809168.05 | F62: 831620.06 | G62: 854072.06 | H62: 876524.07 | K62: =C62 -> 0.12320887 | L62: =D73/$O$50 -> 337.30701 | M62: =E73/$O$50 -> 346.54652 | N62: =F73/$O$50 -> 355.78603 | O62: =G73/$O$50 -> 365.02554 | P62: =H73/$O$50 -> 374.26505
D65: Equity Value | L65: Premium (Discount) to Stock Price
D67: Terminal Multiple | L67: Terminal Multiple
D68: =D57 -> 15 | E68: =E57 -> 15.5 | F68: =F57 -> 16 | G68: =G57 -> 16.5 | H68: =H57 -> 17 | L68: =D68 -> 15 | M68: =E68 -> 15.5 | N68: =F68 -> 16 | O68: =G68 -> 16.5 | P68: =H68 -> 17
B69: WACC | C69: =C58 -> 0.083208871 | D69: =D58-$O$49 -> 981542.62 | E69: =E58-$O$49 -> 1008818.5 | F69: =F58-$O$49 -> 1036094.3 | G69: =G58-$O$49 -> 1063370.2 | H69: =H58-$O$49 -> 1090646 | J69: WACC | K69: =C69 -> 0.083208871 | L69: =L58/$O$51-1 -> 1.2863361 | M69: =M58/$O$51-1 -> 1.3498706 | N69: =N58/$O$51-1 -> 1.413405 | O69: =O58/$O$51-1 -> 1.4769395 | P69: =P58/$O$51-1 -> 1.5404739
C70: =C59 -> 0.093208871 | D70: =D59-$O$49 -> 937550.83 | E70: =E59-$O$49 -> 963514.05 | F70: =F59-$O$49 -> 989477.26 | G70: =G59-$O$49 -> 1015440.5 | H70: =H59-$O$49 -> 1041403.7 | K70: =C70 -> 0.093208871 | L70: =L59/$O$51-1 -> 1.1838648 | M70: =M59/$O$51-1 -> 1.2443416 | N70: =N59/$O$51-1 -> 1.3048185 | O70: =O59/$O$51-1 -> 1.3652954 | P70: =P59/$O$51-1 -> 1.4257723
C71: =C60 -> 0.10320887 | D71: =D60-$O$49 -> 896008.9 | E71: =E60-$O$49 -> 920733.75 | F71: =F60-$O$49 -> 945458.6 | G71: =G60-$O$49 -> 970183.45 | H71: =H60-$O$49 -> 994908.3 | K71: =C71 -> 0.10320887 | L71: =L60/$O$51-1 -> 1.0870999 | M71: =M60/$O$51-1 -> 1.1446922 | N71: =N60/$O$51-1 -> 1.2022846 | O71: =O60/$O$51-1 -> 1.2598769 | P71: =P60/$O$51-1 -> 1.3174692
C72: =C61 -> 0.11320887 | D72: =D61-$O$49 -> 856759.32 | E72: =E61-$O$49 -> 880315.26 | F72: =F61-$O$49 -> 903871.2 | G72: =G61-$O$49 -> 927427.13 | H72: =H61-$O$49 -> 950983.07 | K72: =C72 -> 0.11320887 | L72: =L61/$O$51-1 -> 0.99567472 | M72: =M61/$O$51-1 -> 1.0505443 | N72: =N61/$O$51-1 -> 1.1054138 | O72: =O61/$O$51-1 -> 1.1602833 | P72: =P61/$O$51-1 -> 1.2151529
C73: =C62 -> 0.12320887 | D73: =D62-$O$49 -> 819656.04 | E73: =E62-$O$49 -> 842108.05 | F73: =F62-$O$49 -> 864560.06 | G73: =G62-$O$49 -> 887012.06 | H73: =H62-$O$49 -> 909464.07 | K73: =C73 -> 0.12320887 | L73: =L62/$O$51-1 -> 0.90924895 | M73: =M62/$O$51-1 -> 0.96154708 | N73: =N62/$O$51-1 -> 1.0138452 | O73: =O62/$O$51-1 -> 1.0661433 | P73: =P62/$O$51-1 -> 1.1184414
B77: Football Field Analysis
N80: Best | O80: Base | P80: Worst
L83: Comps | N83: =Model!P414 -> 104.1755 | O83: =Model!O414 -> 94.888311 | P83: =Model!N414 -> 55.704033
L84: DCF (Perpetuity Method) | N84: =H12 -> 279.74701 | O84: =H13 -> 275.01776 | P84: =H14 -> 251.02158
L85: DCF (Exit Multiple Method) | N85: =H49 -> 409.79326 | O85: =H50 -> 389.07761 | P85: =H51 -> 338.97543
L86: 52-week | N86: 184.48 | O86: 176.67 | P86: 86.62

Sheet Inputs
E1: NVIDIA CORPORATION (NASDAQGS:NVDA)
B3: Drivers
B5: All figures in USD thousands unless stated | G5: =Model!K5 -> 2026F | H5: =Model!L5 -> 2027F | I5: =Model!M5 -> 2028F | J5: =Model!N5 -> 2029F | K5: =Model!O5 -> 2030F | L5: =Model!P5 -> Term
B7: Driver Switch | D7: =Outputs!F5 -> 2
B10: Graphics Revenue Segment Growth | G10: {=INDEX(G12:G14,$D$7)} -> 0.1 | H10: {=INDEX(H12:H14,$D$7)} -> 0.08 | I10: {=INDEX(I12:I14,$D$7)} -> 0.06 | J10: {=INDEX(J12:J14,$D$7)} -> 0.05 | K10: {=INDEX(K12:K14,$D$7)} -> 0.04 | L10: {=INDEX(L12:L14,$D$7)} -> 0.03
B12: =[1]Outputs!D14 -> Best Case | G12: 0.15 | H12: 0.1 | I12: 0.08 | J12: 0.06 | K12: 0.05 | L12: 0.04
B13: =[1]Outputs!D15 -> Base Case | G13: 0.1 | H13: 0.08 | I13: 0.06 | J13: 0.05 | K13: 0.04 | L13: 0.03
B14: =[1]Outputs!D16 -> Worst Case | G14: 0.05 | H14: 0.03 | I14: 0.02 | J14: 0.01 | K14: 0.005 | L14: 0.005
B16: Compute & Networking Revenue Growth | G16: {=INDEX(G18:G20,$D$7)} -> 0.65 | H16: {=INDEX(H18:H20,$D$7)} -> 0.35 | I16: {=INDEX(I18:I20,$D$7)} -> 0.2 | J16: {=INDEX(J18:J20,$D$7)} -> 0.12 | K16: {=INDEX(K18:K20,$D$7)} -> 0.08 | L16: {=INDEX(L18:L20,$D$7)} -> 0.05
B18: =$B$12 -> Best Case | G18: 0.8 | H18: 0.5 | I18: 0.3 | J18: 0.18 | K18: 0.1 | L18: 0.06
B19: =$B$13 -> Base Case | G19: 0.65 | H19: 0.35 | I19: 0.2 | J19: 0.12 | K19: 0.08 | L19: 0.05
B20: =$B$14 -> Worst Case | G20: 0.4 | H20: 0.2 | I20: 0.1 | J20: 0.06 | K20: 0.04 | L20: 0.03
B22: Gross Margin | G22: {=INDEX(G24:G26,$D$7)} -> 0.728 | H22: {=INDEX(H24:H26,$D$7)} -> 0.739 | I22: {=INDEX(I24:I26,$D$7)} -> 0.745 | J22: {=INDEX(J24:J26,$D$7)} -> 0.72 | K22: {=INDEX(K24:K26,$D$7)} -> 0.7 | L22: {=INDEX(L24:L26,$D$7)} -> 0.68
B24: =$B$12 -> Best Case | G24: 0.75 | H24: 0.745 | I24: 0.74 | J24: 0.73 | K24: 0.72 | L24: 0.7
B25: =$B$13 -> Base Case | G25: 0.728 | H25: 0.739 | I25: 0.745 | J25: 0.72 | K25: 0.7 | L25: 0.68
B26: =$B$14 -> Worst Case | G26: 0.7 | H26: 0.69 | I26: 0.68 | J26: 0.67 | K26: 0.65 | L26: 0.63
B28: SG&A | G28: {=INDEX(G30:G32,$D$7)} -> 0.042 | H28: {=INDEX(H30:H32,$D$7)} -> 0.04 | I28: {=INDEX(I30:I32,$D$7)} -> 0.038 | J28: {=INDEX(J30:J32,$D$7)} -> 0.035 | K28: {=INDEX(K30:K32,$D$7)} -> 0.033 | L28: {=INDEX(L30:L32,$D$7)} -> 0.033
B30: =$B$12 -> Best Case | G30: 0.046 | H30: 0.044 | I30: 0.042 | J30: 0.04 | K30: 0.038 | L30: 0.04
B31: =$B$13 -> Base Case | G31: 0.042 | H31: 0.04 | I31: 0.038 | J31: 0.035 | K31: 0.033 | L31: 0.033
B32: =$B$14 -> Worst Case | G32: 0.038 | H32: 0.035 | I32: 0.033 | J32: 0.03 | K32: 0.028 | L32: 0.028
B34: R&D | G34: {=INDEX(G36:G38,$D$7)} -> 0.12 | H34: {=INDEX(H36:H38,$D$7)} -> 0.108 | I34: {=INDEX(I36:I38,$D$7)} -> 0.1 | J34: {=INDEX(J36:J38,$D$7)} -> 0.09 | K34: {=INDEX(K36:K38,$D$7)} -> 0.085 | L34: {=INDEX(L36:L38,$D$7)} -> 0.085
B36: =$B$12 -> Best Case | G36: 0.13 | H36: 0.12 | I36: 0.115 | J36: 0.11 | K36: 0.105 | L36: 0.105
B37: =$B$13 -> Base Case | G37: 0.12 | H37: 0.108 | I37: 0.1 | J37: 0.09 | K37: 0.085 | L37: 0.085
B38: =$B$14 -> Worst Case | G38: 0.11 | H38: 0.098 | I38: 0.09 | J38: 0.082 | K38: 0.075 | L38: 0.075
B40: Capex % | G40: {=INDEX(G42:G44,$D$7)} -> 0.027 | H40: {=INDEX(H42:H44,$D$7)} -> 0.028 | I40: {=INDEX(I42:I44,$D$7)} -> 0.028 | J40: {=INDEX(J42:J44,$D$7)} -> 0.027 | K40: {=INDEX(K42:K44,$D$7)} -> 0.026 | L40: {=INDEX(L42:L44,$D$7)} -> 0.025
B42: =$B$12 -> Best Case | G42: 0.023 | H42: 0.023 | I42: 0.024 | J42: 0.024 | K42: 0.023 | L42: 0.02
B43: =$B$13 -> Base Case | G43: 0.027 | H43: 0.028 | I43: 0.028 | J43: 0.027 | K43: 0.026 | L43: 0.025
B44: =$B$14 -> Worst Case | G44: 0.035 | H44: 0.037 | I44: 0.038 | J44: 0.038 | K44: 0.035 | L44: 0.03
B46: Working Capital
B47: Accounts Receivable | E47: (Days) | G47: 64 | H47: 63 | I47: 62 | J47: 61 | K47: 60 | L47: 60
B48: Inventory | E48: (Days) | G48: 31 | H48: 30 | I48: 29 | J48: 29 | K48: 28 | L48: 28
B49: Accounts Payable | E49: (Days) | G49: 48 | H49: 49 | I49: 50 | J49: 50 | K49: 50 | L49: =K49 -> 50
B51: Net Interest Income (% of Revenue) | G51: {=INDEX(G53:G55,$D$7)} -> 0.004 | H51: {=INDEX(H53:H55,$D$7)} -> 0.0045 | I51: {=INDEX(I53:I55,$D$7)} -> 0.005 | J51: {=INDEX(J53:J55,$D$7)} -> 0.005 | K51: {=INDEX(K53:K55,$D$7)} -> 0.005 | L51: {=INDEX(L53:L55,$D$7)} -> 0.005
B53: =$B$12 -> Best Case | G53: 0.006 | H53: 0.0065 | I53: 0.007 | J53: 0.007 | K53: 0.007 | L53: 0.007
B54: =$B$13 -> Base Case | G54: 0.004 | H54: 0.0045 | I54: 0.005 | J54: 0.005 | K54: 0.005 | L54: 0.005
B55: =$B$14 -> Worst Case | G55: 0.002 | H55: 0.0025 | I55: 0.003 | J55: 0.003 | K55: 0.003 | L55: 0.003
B58: Weighted Average Cost of Capital
B60: All figures in USD thousands unless stated
H62: Average | I62: Debt/ | J62: Debt/ | K62: Levered | L62: Unlevered
B63: Name | D63: Ticker | F63: Debt | G63: Equity | H63: Tax Rate | I63: Equity | J63: Capital | K63: Beta | L63: Beta
B65: Advanced Micro Devices, Inc. | D65: NasdaqGS:AMD | F65: 3886 | G65: 255419.37 | H65: 0.164009 | I65: =F65/G65 -> 0.015214195 | J65: =F65/(F65+G65) -> 0.014986192 | K65: 1.91577 | L65: =K65/(1+(1-H65)*I65) -> 1.8917095
B66: Intel Corporation | D66: NasdaqGS:INTC | F66: 50757 | G66: 137593.83 | H66: 0.125595 | I66: =F66/G66 -> 0.3688901 | J66: =F66/(F66+G66) -> 0.26948117 | K66: 1.22955 | L66: =K66/(1+(1-H66)*I66) -> 0.92967473
B67: Broadcom Inc. | D67: NasdaqGS:AVGO | F67: 64229 | G67: 1628932.6 | H67: 0.1312523 | I67: =F67/G67 -> 0.039430115 | J67: =F67/(F67+G67) -> 0.037934359 | K67: 1.17221 | L67: =K67/(1+(1-H67)*I67) -> 1.1333861
B68: QUALCOMM Incorporated | D68: NasdaqGS:QCOM | F68: 14788 | G68: 179161.43 | H68: 0.0761808 | I68: =F68/G68 -> 0.082540087 | J68: =F68/(F68+G68) -> 0.076246679 | K68: 1.21123 | L68: =K68/(1+(1-H68)*I68) -> 1.1254147
B69: Micron Technology, Inc. | D69: NasdaqGS:MU | F69: 16213 | G69: 182115.23 | H69: 0.154085 | I69: =F69/G69 -> 0.089026053 | J69: =F69/(F69+G69) -> 0.081748323 | K69: 1.46742 | L69: =K69/(1+(1-H69)*I69) -> 1.3646503
B70: Texas Instruments Incorporated | D70: NasdaqGS:TXN | F70: 14043 | G70: 163071.93 | H70: 0.1138598 | I70: =F70/G70 -> 0.08611537 | J70: =F70/(F70+G70) -> 0.079287498 | K70: 1.00556 | L70: =K70/(1+(1-H70)*I70) -> 0.9342659
G72: Average | H72: =AVERAGE(H65:H70) -> 0.12749698 | I72: =AVERAGE(I65:I70) -> 0.11353599 | J72: =AVERAGE(J65:J70) -> 0.093280703 | K72: =AVERAGE(K65:K70) -> 1.3336233 | L72: =AVERAGE(L65:L70) -> 1.2298502
G73: Median | H73: =MEDIAN(H65:H70) -> 0.12842365 | I73: =MEDIAN(I65:I70) -> 0.084327728 | J73: =MEDIAN(J65:J70) -> 0.077767089 | K73: =MEDIAN(K65:K70) -> 1.22039 | L73: =MEDIAN(L65:L70) -> 1.1294004
B76: Cost of Equity | H76: Cost of Debt
B78: Risk Free Rate | F78: 0.0419 | H78: Pre-Tax Cost of Debt | L78: 0.027
B79: Equity Risk Premium | F79: 0.05 | H79: Tax Rate | L79: 0.125
B80: Leveraged Beta | F80: 1.23 | H80: After-Tax Cost of Debt | L80: =L78*(1-L79) -> 0.023625
B81: Cost of Equity | F81: =F78+F80*F79 -> 0.1034
B83: Capital Structure | H83: Weighted Average Cost of Capital
F85: Current | K85: Weight | L85: Cost
B86: Total Debt | E86: 10598 | F86: =E86/$E$88 -> 0.0023958523 | H86: Debt Capital | K86: =F86 -> 0.0023958523 | L86: =L80 -> 0.023625
B87: Market Capitalization | E87: 4412880 | F87: =E87/$E$88 -> 0.99760415 | H87: Equity Capital | K87: =F87 -> 0.99760415 | L87: =F81 -> 0.1034
B88: Total Capitalization | E88: =SUM(E86:E87) -> 4423478 | F88: =SUM(F86:F87) -> 1
B90: Debt / Equity | F90: =F86/F87 -> 0.0024016062 | H90: Weighted Average Cost of Capital | L90: =SUMPRODUCT(K86:K87,L86:L87) -> 0.10320887
B93: Other Inputs
B95: All figures in USD thousands unless stated
B97: Dates | H97: Other Inputs
B98: Valuation Date | E98: (YY-MM-DD) | F98: 45920 | H98: First Year Tax Depreciation | L98: 0.3
B99: First Expected Cash Flow | E99: (YY-MM-DD) | F99: 46053 | H99: Blended Tax Depreciation Rate | L99: 0.12
B100: First Fiscal Year End for Forecast | E100: (YY-MM-DD) | F100: 46053 | H100: First Year Accounting Depreciation | L100: 0.5
B101: First Year of Forecast | E101: (YYYY) | F101: =YEAR(F100) -> 2026 | H101: Useful Life: Existing Assets | K101: (Years) | L101: 6
B102: Incorrect Date Set for Valuation? | F102: =IF(F98>F99,1,0) -> 0 | H102: Useful Life: New Assets | K102: (Years) | L102: 6
B103: Incorrect Date Set for First Cash Flow? | F103: =IF(F99>F100,1,0) -> 0
B104: Days in Period | F104: 365
B106: Valuation
B107: Shares Outstanding | E107: (FD 000) | F107: 2430
B108: Current Stock Price | E108: (US$/sh) | F108: 176.67
B109: Terminal Growth Rate | F109: 0.03
B110: Terminal EBITDA Multiple 1 | F110: 16
B111: Weighted Average Cost of Capital (WACC) | F111: =L90 -> 0.10320887
B112: Terminal Growth Greater Than or Equal To WACC? | F112: =IF(F109>=F111,1,0) -> 0

Sheet Model
D1: NVIDIA CORPORATION (NASDAQGS:NVDA)
B3: Revenue Schedule
B5: All figures in USD thousands unless stated | F5: ='Income Statement'!C5 -> 44227 | G5: ='Income Statement'!D5 -> 44591 | H5: ='Income Statement'!E5 -> 44955 | I5: ='Income Statement'!F5 -> 45319 | J5: ='Income Statement'!G5 -> 45683 | K5: 2026F | L5: 2027F | M5: 2028F | N5: 2029F | O5: 2030F | P5: Term
B6: {=CONCATENATE("Model Running: ",INDEX(Inputs!$B$12:$B$14,Inputs!$D$7)," Drivers")} -> Model Running: Base Case Drivers
B8: Days in Period | C8: =Inputs!F104 -> 365 | F8: =$C$8 -> 365 | G8: =$C$8 -> 365 | H8: =$C$8 -> 365 | I8: =$C$8 -> 365 | J8: =$C$8 -> 365 | K8: =$C$8 -> 365 | L8: =$C$8 -> 365 | M8: =$C$8 -> 365 | ... P8: =$C$8 -> 365
B10: OPERATIONS
B12: Graphics Growth | G12: =(G13-F13)/F13 -> 0.61358552 | H12: =(H13-G13)/G13 -> -0.2496849 | I12: =(I13-H13)/H13 -> 0.13530993 | J12: =(J13-I13)/I13 -> 0.058222978 | K12: =Inputs!G10 -> 0.1 | L12: =Inputs!H10 -> 0.08 | M12: =Inputs!I10 -> 0.06 | N12: =Inputs!J10 -> 0.05 | O12: =Inputs!K10 -> 0.04 | P12: =Inputs!L10 -> 0.03
B13: Graphics Revenue | F13: 9834 | G13: 15868 | H13: 11906 | I13: 13517 | J13: 14304 | K13: =J13*(1+K12) -> 15734.4 | L13: =K13*(1+L12) -> 16993.152 | M13: =L13*(1+M12) -> 18012.741 | N13: =M13*(1+N12) -> 18913.378 | O13: =N13*(1+O12) -> 19669.913 | P13: =O13*(1+P12) -> 20260.011
B15: Compute & Networking Growth | G15: =(G16-F16)/F16 -> 0.61467622 | H15: =(H16-G16)/G16 -> 0.36411371 | I15: =(I16-H16)/H16 -> 2.1460711 | J15: =(J16-I16)/I16 -> 1.4510706 | K15: =Inputs!G16 -> 0.65 | L15: =Inputs!H16 -> 0.35 | M15: =Inputs!I16 -> 0.2 | N15: =Inputs!J16 -> 0.12 | O15: =Inputs!K16 -> 0.08 | P15: =Inputs!L16 -> 0.05
B16: Compute & Networking Revenue | F16: 6841 | G16: 11046 | H16: 15068 | I16: 47405 | J16: 116193 | K16: =J16*(1+K15) -> 191718.45 | L16: =K16*(1+L15) -> 258819.91 | M16: =L16*(1+M15) -> 310583.89 | N16: =M16*(1+N15) -> 347853.96 | O16: =N16*(1+O15) -> 375682.27 | P16: =O16*(1+P15) -> 394466.39
B18: REVENUE
B20: Graphics Revenue | F20: =F13 -> 9834 | G20: =G13 -> 15868 | H20: =H13 -> 11906 | I20: =I13 -> 13517 | J20: =J13 -> 14304 | K20: =K13 -> 15734.4 | L20: =L13 -> 16993.152 | M20: =M13 -> 18012.741 | ... P20: =P13 -> 20260.011
B21: Compute & Networking Revenue | F21: =F16 -> 6841 | G21: =G16 -> 11046 | H21: =H16 -> 15068 | I21: =I16 -> 47405 | J21: =J16 -> 116193 | K21: =K16 -> 191718.45 | L21: =L16 -> 258819.91 | M21: =M16 -> 310583.89 | ... P21: =P16 -> 394466.39
B22: Revenue | F22: =SUM(F20:F21) -> 16675 | G22: =SUM(G20:G21) -> 26914 | H22: =SUM(H20:H21) -> 26974 | I22: =SUM(I20:I21) -> 60922 | J22: =SUM(J20:J21) -> 130497 | K22: =SUM(K20:K21) -> 207452.85 | L22: =SUM(L20:L21) -> 275813.06 | M22: =SUM(M20:M21) -> 328596.63 | ... P22: =SUM(P20:P21) -> 414726.4
B25: Cost Schedule
B27: All figures in USD thousands unless stated | F27: =F$5 -> 44227 | G27: =G$5 -> 44591 | H27: =H$5 -> 44955 | I27: =I$5 -> 45319 | J27: =J$5 -> 45683 | K27: =K$5 -> 2026F | L27: =L$5 -> 2027F | M27: =M$5 -> 2028F | ... P27: =P$5 -> Term
B28: =$B$6 -> Model Running: Base Case Drivers
B30: Revenue | F30: =F22 -> 16675 | G30: =G22 -> 26914 | H30: =H22 -> 26974 | I30: =I22 -> 60922 | J30: =J22 -> 130497 | K30: =K22 -> 207452.85 | L30: =L22 -> 275813.06 | M30: =M22 -> 328596.63 | ... P30: =P22 -> 414726.4
B31: Revenue Growth (%) | G31: =(G30/F30)-1 -> 0.61403298 | H31: =(H30/G30)-1 -> 0.002229323 | I31: =(I30/H30)-1 -> 1.2585453 | J31: =(J30/I30)-1 -> 1.1420341 | K31: =(K30/J30)-1 -> 0.58971356 | L31: =(L30/K30)-1 -> 0.32952167 | M31: =(M30/L30)-1 -> 0.19137444 | N31: =(N30/M30)-1 -> 0.1161628 | ... P31: =(P30/O30)-1 -> 0.049004942
B33: Gross Profit | F33: ='Income Statement'!C14 -> 10557 | G33: ='Income Statement'!D14 -> 17475 | H33: ='Income Statement'!E14 -> 15356 | I33: ='Income Statement'!F14 -> 44301 | J33: ='Income Statement'!G14 -> 97858 | K33: =K30*K34 -> 151025.67 | L33: =L30*L34 -> 203825.85 | M33: =M30*M34 -> 244804.49 | N33: =N30*N34 -> 264072.48 | O33: =O30*O34 -> 276746.53 | P33: =P30*P34 -> 282013.95
B34: Gross Margin (%) | G34: =G33/G30 -> 0.64929033 | H34: =H33/H30 -> 0.56928894 | I34: =I33/I30 -> 0.72717573 | J34: =J33/J30 -> 0.74988697 | K34: =Inputs!G22 -> 0.728 | L34: =Inputs!H22 -> 0.739 | M34: =Inputs!I22 -> 0.745 | N34: =Inputs!J22 -> 0.72 | O34: =Inputs!K22 -> 0.7 | P34: =Inputs!L22 -> 0.68
B36: Revenue Growth (%) | G36: =G31 -> 0.61403298 | H36: =H31 -> 0.002229323 | I36: =I31 -> 1.2585453 | J36: =J31 -> 1.1420341 | K36: =K31 -> 0.58971356 | L36: =L31 -> 0.32952167 | M36: =M31 -> 0.19137444 | N36: =N31 -> 0.1161628 | ... P36: =P31 -> 0.049004942
B37: Cost Margin (%) | G37: =1-G38 -> 0.35070967 | H37: =1-H38 -> 0.43071106 | I37: =1-I38 -> 0.27282427 | J37: =1-J38 -> 0.25011303 | K37: =1-K38 -> 0.272 | L37: =1-L38 -> 0.261 | M37: =1-M38 -> 0.255 | N37: =1-N38 -> 0.28 | ... P37: =1-P38 -> 0.32
B38: Gross Margin (%) | G38: =G34 -> 0.64929033 | H38: =H34 -> 0.56928894 | I38: =I34 -> 0.72717573 | J38: =J34 -> 0.74988697 | K38: =K34 -> 0.728 | L38: =L34 -> 0.739 | M38: =M34 -> 0.745 | N38: =N34 -> 0.72 | ... P38: =P34 -> 0.68
B41: Income Statement
B43: All figures in USD thousands unless stated | F43: =F$5 -> 44227 | G43: =G$5 -> 44591 | H43: =H$5 -> 44955 | I43: =I$5 -> 45319 | J43: =J$5 -> 45683 | K43: =K$5 -> 2026F | L43: =L$5 -> 2027F | M43: =M$5 -> 2028F | ... P43: =P$5 -> Term
B44: =$B$6 -> Model Running: Base Case Drivers
B46: Revenue | F46: =F22 -> 16675 | G46: =G22 -> 26914 | H46: =H22 -> 26974 | I46: =I22 -> 60922 | J46: =J22 -> 130497 | K46: =K22 -> 207452.85 | L46: =L22 -> 275813.06 | M46: =M22 -> 328596.63 | ... P46: =P22 -> 414726.4
B47: COGS | F47: ='Income Statement'!C13 -> 6118 | G47: ='Income Statement'!D13 -> 9439 | H47: ='Income Statement'!E13 -> 11618 | I47: ='Income Statement'!F13 -> 16621 | J47: ='Income Statement'!G13 -> 32639 | K47: =K30*K37 -> 56427.175 | L47: =L30*L37 -> 71987.209 | M47: =M30*M37 -> 83792.141 | N47: =N30*N37 -> 102694.85 | O47: =O30*O37 -> 118605.66 | P47: =P30*P37 -> 132712.45
B48: Gross Profit | F48: =F46-F47 -> 10557 | G48: =G46-G47 -> 17475 | H48: =H46-H47 -> 15356 | I48: =I46-I47 -> 44301 | J48: =J46-J47 -> 97858 | K48: =K46-K47 -> 151025.67 | L48: =L46-L47 -> 203825.85 | M48: =M46-M47 -> 244804.49 | ... P48: =P46-P47 -> 282013.95
B50: SG&A | F50: ='Income Statement'!C16 -> 1912 | G50: ='Income Statement'!D16 -> 2166 | H50: ='Income Statement'!E16 -> 2440 | I50: ='Income Statement'!F16 -> 2654 | J50: ='Income Statement'!G16 -> 3491 | K50: =K75 -> 8713.0197 | L50: =L75 -> 11032.522 | M50: =M75 -> 12486.672 | N50: =N75 -> 12836.857 | O50: =O75 -> 13046.622 | P50: =P75 -> 13685.971
B51: R&D | F51: ='Income Statement'!C17 -> 3924 | G51: ='Income Statement'!D17 -> 5268 | H51: ='Income Statement'!E17 -> 7339 | I51: ='Income Statement'!F17 -> 8675 | J51: ='Income Statement'!G17 -> 12914 | K51: =K78 -> 24894.342 | L51: =L78 -> 29787.81 | M51: =M78 -> 32859.663 | N51: =N78 -> 33009.06 | O51: =O78 -> 33604.936 | P51: =P78 -> 35251.744
B52: EBITDA | F52: =F47-SUM(F50:F51) -> 282 | G52: =G47-SUM(G50:G51) -> 2005 | H52: =H47-SUM(H50:H51) -> 1839 | I52: =I47-SUM(I50:I51) -> 5292 | J52: =J47-SUM(J50:J51) -> 16234 | K52: =K47-SUM(K50:K51) -> 22819.814 | L52: =L47-SUM(L50:L51) -> 31166.876 | M52: =M47-SUM(M50:M51) -> 38445.806 | ... P52: =P47-SUM(P50:P51) -> 83774.732
B54: Depreciation | F54: =-'Balance Sheet'!C23 -> 1408 | G54: =-'Balance Sheet'!D23 -> 1903 | H54: =-'Balance Sheet'!E23 -> 2694 | I54: =-'Balance Sheet'!F23 -> 3509 | J54: =-'Balance Sheet'!G23 -> 4401 | K54: =K121 -> 1812.7689 | L54: =L121 -> 2923.1016 | M54: =M121 -> 4333.3909 | N54: =N121 -> 5925.3429 | O54: =O121 -> 7607.1658 | P54: =P88 -> 10368.16
B55: EBIT | F55: =F52-F54 -> -1126 | G55: =G52-G54 -> 102 | H55: =H52-H54 -> -855 | I55: =I52-I54 -> 1783 | J55: =J52-J54 -> 11833 | K55: =K52-K54 -> 21007.045 | L55: =L52-L54 -> 28243.774 | M55: =M52-M54 -> 34112.415 | ... P55: =P52-P54 -> 73406.572
B57: Interest | F57: ='Income Statement'!C27 -> -127 | G57: ='Income Statement'!D27 -> -207 | H57: ='Income Statement'!E27 -> 5 | I57: ='Income Statement'!F27 -> 609 | J57: ='Income Statement'!G27 -> 1539 | K57: =K$46*Inputs!G$51 -> 829.8114 | L57: =L$46*Inputs!H$51 -> 1241.1588 | M57: =M$46*Inputs!I$51 -> 1642.9832 | N57: =N$46*Inputs!J$51 -> 1833.8367 | O57: =O$46*Inputs!K$51 -> 1976.7609 | P57: =P$46*Inputs!L$51 -> 2073.632
B58: EBT | F58: =F55-F57 -> -999 | G58: =G55-G57 -> 309 | H58: =H55-H57 -> -860 | I58: =I55-I57 -> 1174 | J58: =J55-J57 -> 10294 | K58: =K55-K57 -> 20177.233 | L58: =L55-L57 -> 27002.615 | M58: =M55-M57 -> 32469.432 | ... P58: =P55-P57 -> 71332.94
B60: Current Tax | F60: ='Income Statement'!C80 -> 359 | G60: ='Income Statement'!D80 -> 595 | H60: ='Income Statement'!E80 -> 1977 | I60: ='Income Statement'!F80 -> 6547 | J60: ='Income Statement'!G80 -> 15623 | K60: =K212 -> 0 | L60: =L212 -> 3304.6516 | M60: =M212 -> 4364.5274 | N60: =N212 -> 6528.1915 | O60: =O212 -> 8290.0798 | P60: =Inputs!L79*Model!P58 -> 8916.6175
B61: Deferred Tax | F61: ='Income Statement'!C83 -> -282 | G61: ='Income Statement'!D83 -> -406 | H61: ='Income Statement'!E83 -> -2164 | I61: ='Income Statement'!F83 -> -2489 | J61: ='Income Statement'!G83 -> -4477 | K61: =K213 -> 2522.1541 | L61: =L213 -> 70.675342 | M61: =M213 -> -305.8484 | N61: =N213 -> -391.97181 | O61: =O213 -> -493.80845 | P61: =P213 -> 0
B62: Total Tax | F62: =SUM(F60:F61) -> 77 | G62: =SUM(G60:G61) -> 189 | H62: =SUM(H60:H61) -> -187 | I62: =SUM(I60:I61) -> 4058 | J62: =SUM(J60:J61) -> 11146 | K62: =SUM(K60:K61) -> 2522.1541 | L62: =SUM(L60:L61) -> 3375.3269 | M62: =SUM(M60:M61) -> 4058.679 | ... P62: =SUM(P60:P61) -> 8916.6175
B64: Net Income | F64: =F58-F62 -> -1076 | G64: =G58-G62 -> 120 | H64: =H58-H62 -> -673 | I64: =I58-I62 -> -2884 | J64: =J58-J62 -> -852 | K64: =K58-K62 -> 17655.079 | L64: =L58-L62 -> 23627.288 | M64: =M58-M62 -> 28410.753 | ... P64: =P58-P62 -> 62416.323
B67: Operational Expense Schedule
B69: All figures in USD thousands unless stated | F69: =F$5 -> 44227 | G69: =G$5 -> 44591 | H69: =H$5 -> 44955 | I69: =I$5 -> 45319 | J69: =J$5 -> 45683 | K69: =K$5 -> 2026F | L69: =L$5 -> 2027F | M69: =M$5 -> 2028F | ... P69: =P$5 -> Term
B70: =$B$6 -> Model Running: Base Case Drivers
B72: Revenue | F72: =F46 -> 16675 | G72: =G46 -> 26914 | H72: =H46 -> 26974 | I72: =I46 -> 60922 | J72: =J46 -> 130497 | K72: =K46 -> 207452.85 | L72: =L46 -> 275813.06 | M72: =M46 -> 328596.63 | ... P72: =P46 -> 414726.4
B75: =B50 -> SG&A | F75: =F50 -> 1912 | G75: =G50 -> 2166 | H75: =H50 -> 2440 | I75: =I50 -> 2654 | J75: =J50 -> 3491 | K75: =K72*K76 -> 8713.0197 | L75: =L72*L76 -> 11032.522 | M75: =M72*M76 -> 12486.672 | N75: =N72*N76 -> 12836.857 | O75: =O72*O76 -> 13046.622 | P75: =P72*P76 -> 13685.971
B76: SG&A % | F76: =F75/F72 -> 0.11466267 | G76: =G75/G72 -> 0.080478561 | H76: =H75/H72 -> 0.090457478 | I76: =I75/I72 -> 0.043563901 | J76: =J75/J72 -> 0.026751573 | K76: =Inputs!G28 -> 0.042 | L76: =Inputs!H28 -> 0.04 | M76: =Inputs!I28 -> 0.038 | N76: =Inputs!J28 -> 0.035 | O76: =Inputs!K28 -> 0.033 | P76: =Inputs!L28 -> 0.033
B78: =B51 -> R&D | F78: =F51 -> 3924 | G78: =G51 -> 5268 | H78: =H51 -> 7339 | I78: =I51 -> 8675 | J78: =J51 -> 12914 | K78: =K72*K79 -> 24894.342 | L78: =L72*L79 -> 29787.81 | M78: =M72*M79 -> 32859.663 | N78: =N72*N79 -> 33009.06 | O78: =O72*O79 -> 33604.936 | P78: =P72*P79 -> 35251.744
B79: R&D % | F79: =F78/F72 -> 0.23532234 | G79: =G78/G72 -> 0.19573456 | H79: =H78/H72 -> 0.27207681 | I79: =I78/I72 -> 0.14239519 | J79: =J78/J72 -> 0.098960129 | K79: =Inputs!G34 -> 0.12 | L79: =Inputs!H34 -> 0.108 | M79: =Inputs!I34 -> 0.1 | N79: =Inputs!J34 -> 0.09 | O79: =Inputs!K34 -> 0.085 | P79: =Inputs!L34 -> 0.085
B82: Depreciation Schedule
B84: All figures in USD thousands unless stated | F84: =F$5 -> 44227 | G84: =G$5 -> 44591 | H84: =H$5 -> 44955 | I84: =I$5 -> 45319 | J84: =J$5 -> 45683 | K84: =K$5 -> 2026F | L84: =L$5 -> 2027F | M84: =M$5 -> 2028F | ... P84: =P$5 -> Term
B85: =$B$6 -> Model Running: Base Case Drivers
B87: Capex % | F87: =F88/F46 -> 0.067646177 | G87: =G88/G46 -> 0.036263655 | H87: =H88/H46 -> 0.067954326 | I87: =I88/I46 -> 0.017547027 | J87: =J88/J46 -> 0.024797505 | K87: =Inputs!G40 -> 0.027 | L87: =Inputs!H40 -> 0.028 | M87: =Inputs!I40 -> 0.028 | N87: =Inputs!J40 -> 0.027 | O87: =Inputs!K40 -> 0.026 | P87: =Inputs!L40 -> 0.025
B88: Capital Expenditure | F88: =-'Cashflow Statement'!C27 -> 1128 | G88: =-'Cashflow Statement'!D27 -> 976 | H88: =-'Cashflow Statement'!E27 -> 1833 | I88: =-'Cashflow Statement'!F27 -> 1069 | J88: =-'Cashflow Statement'!G27 -> 3236 | K88: =K46*K87 -> 5601.2269 | L88: =L46*L87 -> 7722.7657 | M88: =M46*M87 -> 9200.7056 | N88: =N46*N87 -> 9902.718 | O88: =O46*O87 -> 10279.157 | P88: =P46*P87 -> 10368.16
B91: EXISTING ASSET DEPRECIATION | D91: Years | K91: Percent of Full Year
B92: Useful Life: Existing Assets | D92: =Inputs!$L$101 -> 6 | K92: 1 | L92: =K92+1 -> 2 | M92: =L92+1 -> 3 | N92: =M92+1 -> 4 | O92: =N92+1 -> 5
B93: =CONCATENATE("PP&E at End of ",2025) -> PP&E at End of 2025 | D93: ='Balance Sheet'!G24 -> 8076 | K93: =MIN($D92-SUM($J93:J93),1) -> 1 | L93: =MIN($D92-SUM($J93:K93),1) -> 1 | M93: =MIN($D92-SUM($J93:L93),1) -> 1 | N93: =MIN($D92-SUM($J93:M93),1) -> 1 | O93: =MIN($D92-SUM($J93:N93),1) -> 1
B97: NEW ASSET DEPRECIATION 1 | D97: Years | K97: Percent of Full Year
B98: Useful Life: New Assets | D98: =Inputs!$L$102 -> 6 | K98: 1 | L98: =K98+1 -> 2 | M98: =L98+1 -> 3 | N98: =M98+1 -> 4 | O98: =N98+1 -> 5
B99: First Year Accounting Depreciation | D99: =Inputs!L100 -> 0.5 | K99: =IF(J99="",$D$99,MIN($D98-SUM($J99:J99),1)) -> 0.5 | L99: =IF(K99="",$D$99,MIN($D98-SUM($J99:K99),1)) -> 1 | M99: =IF(L99="",$D$99,MIN($D98-SUM($J99:L99),1)) -> 1 | N99: =IF(M99="",$D$99,MIN($D98-SUM($J99:M99),1)) -> 1 | O99: =IF(N99="",$D$99,MIN($D98-SUM($J99:N99),1)) -> 1
K101: Percent of Full Year
H102: Year | I102: Life | K102: =K84 -> 2026F | L102: =L84 -> 2027F | M102: =M84 -> 2028F | N102: =N84 -> 2029F | O102: =O84 -> 2030F
H103: =K84 -> 2026F | I103: =$D$98 -> 6 | K103: =K99 -> 0.5 | L103: =L99 -> 1 | M103: =M99 -> 1 | N103: =N99 -> 1 | O103: =O99 -> 1
H104: =L84 -> 2027F | I104: =$D$98 -> 6 | K104: =J103 -> 0 | L104: =K103 -> 0.5 | M104: =L103 -> 1 | N104: =M103 -> 1 | O104: =N103 -> 1
H105: =M84 -> 2028F | I105: =$D$98 -> 6 | K105: =J104 -> 0 | L105: =K104 -> 0 | M105: =L104 -> 0.5 | N105: =M104 -> 1 | O105: =N104 -> 1
H106: =N84 -> 2029F | I106: =$D$98 -> 6 | K106: =J105 -> 0 | L106: =K105 -> 0 | M106: =L105 -> 0 | N106: =M105 -> 0.5 | O106: =N105 -> 1
H107: =O84 -> 2030F | I107: =$D$98 -> 6 | K107: =J106 -> 0 | L107: =K106 -> 0 | M107: =L106 -> 0 | N107: =M106 -> 0 | O107: =N106 -> 0.5
K109: Amounts for Depreciation
H110: Year | I110: Capex | J110: Per Yr | K110: =K102 -> 2026F | L110: =L102 -> 2027F | M110: =M102 -> 2028F | N110: =N102 -> 2029F | O110: =O102 -> 2030F
H111: =H103 -> 2026F | I111: =K88 -> 5601.2269 | J111: =I111/I103 -> 933.53782 | K111: =$J111*K103 -> 466.76891 | L111: =$J111*L103 -> 933.53782 | M111: =$J111*M103 -> 933.53782 | N111: =$J111*N103 -> 933.53782 | O111: =$J111*O103 -> 933.53782
H112: =H104 -> 2027F | I112: =L88 -> 7722.7657 | J112: =I112/I104 -> 1287.1276 | K112: =$J112*K104 -> 0 | L112: =$J112*L104 -> 643.56381 | M112: =$J112*M104 -> 1287.1276 | N112: =$J112*N104 -> 1287.1276 | O112: =$J112*O104 -> 1287.1276
H113: =H105 -> 2028F | I113: =M88 -> 9200.7056 | J113: =I113/I105 -> 1533.4509 | K113: =$J113*K105 -> 0 | L113: =$J113*L105 -> 0 | M113: =$J113*M105 -> 766.72547 | N113: =$J113*N105 -> 1533.4509 | O113: =$J113*O105 -> 1533.4509
H114: =H106 -> 2029F | I114: =N88 -> 9902.718 | J114: =I114/I106 -> 1650.453 | K114: =$J114*K106 -> 0 | L114: =$J114*L106 -> 0 | M114: =$J114*M106 -> 0 | N114: =$J114*N106 -> 825.2265 | O114: =$J114*O106 -> 1650.453
H115: =H107 -> 2030F | I115: =O88 -> 10279.157 | J115: =I115/I107 -> 1713.1928 | K115: =$J115*K107 -> 0 | L115: =$J115*L107 -> 0 | M115: =$J115*M107 -> 0 | N115: =$J115*N107 -> 0 | O115: =$J115*O107 -> 856.5964
B118: TOTAL ASSET DEPRECIATION 2
B119: Existing Assets | K119: =($D$93/$D$92)*K93 -> 1346 | L119: =($D$93/$D$92)*L93 -> 1346 | M119: =($D$93/$D$92)*M93 -> 1346 | N119: =($D$93/$D$92)*N93 -> 1346 | O119: =($D$93/$D$92)*O93 -> 1346
B120: New Assets | K120: =SUM(K111:K115) -> 466.76891 | L120: =SUM(L111:L115) -> 1577.1016 | M120: =SUM(M111:M115) -> 2987.3909 | N120: =SUM(N111:N115) -> 4579.3429 | O120: =SUM(O111:O115) -> 6261.1658
B121: Total Depreciation | K121: =SUM(K119:K120) -> 1812.7689 | L121: =SUM(L119:L120) -> 2923.1016 | M121: =SUM(M119:M120) -> 4333.3909 | N121: =SUM(N119:N120) -> 5925.3429 | O121: =SUM(O119:O120) -> 7607.1658
O124: All PP&E and capital expenditure is assumed depreciable (i.e. no land balance).
O125: This schedule calculates depreciation on a straight-line basis.
B128: Asset Schedule
B130: All figures in USD thousands unless stated | J130: =J$5 -> 45683 | K130: =K$5 -> 2026F | L130: =L$5 -> 2027F | M130: =M$5 -> 2028F | N130: =N$5 -> 2029F | O130: =O$5 -> 2030F
B131: =$B$6 -> Model Running: Base Case Drivers
B133: Capital Expenditure | K133: =K88 -> 5601.2269 | L133: =L88 -> 7722.7657 | M133: =M88 -> 9200.7056 | N133: =N88 -> 9902.718 | O133: =O88 -> 10279.157
B135: First Year Tax Depreciation | D135: =Inputs!L98 -> 0.3
B136: Blended Tax Depreciation Rate | D136: =Inputs!L99 -> 0.12
B139: PROPERTY PLANT & EQUIPMENT
B140: Beginning | K140: =J143 -> 8076 | L140: =K143 -> 11864.458 | M140: =L143 -> 16664.122 | N140: =M143 -> 21531.437 | O140: =N143 -> 25508.812
B141: Capital Expenditure | K141: =K133 -> 5601.2269 | L141: =L133 -> 7722.7657 | M141: =M133 -> 9200.7056 | N141: =N133 -> 9902.718 | O141: =O133 -> 10279.157
B142: Accounting Depreciation | K142: =-K121 -> -1812.7689 | L142: =-L121 -> -2923.1016 | M142: =-M121 -> -4333.3909 | N142: =-N121 -> -5925.3429 | O142: =-O121 -> -7607.1658
B143: Ending | J143: ='Balance Sheet'!G24 -> 8076 | K143: =SUM(K140:K142) -> 11864.458 | L143: =SUM(L140:L142) -> 16664.122 | M143: =SUM(M140:M142) -> 21531.437 | N143: =SUM(N140:N142) -> 25508.812 | O143: =SUM(O140:O142) -> 28180.803
B145: TAX BASIS
B146: Beginning | K146: =J149 -> 988 | L146: =K149 -> 6269.0228 | M146: =L149 -> 12961.486 | N146: =M149 -> 20275.588 | O146: =N149 -> 27388.738
B147: Capital Expenditure | K147: =K133 -> 5601.2269 | L147: =L133 -> 7722.7657 | M147: =M133 -> 9200.7056 | N147: =N133 -> 9902.718 | O147: =O133 -> 10279.157
B148: Tax Depreciation | K148: =-(K146+K147*$D$135)*$D$136 -> -320.20417 | L148: =-(L146+L147*$D$135)*$D$136 -> -1030.3023 | M148: =-(M146+M147*$D$135)*$D$136 -> -1886.6037 | N148: =-(N146+N147*$D$135)*$D$136 -> -2789.5684 | O148: =-(O146+O147*$D$135)*$D$136 -> -3656.6982
B149: Ending | J149: ='Balance Sheet'!G24-('Balance Sheet'!G47/Model!D188) -> 988 | K149: =SUM(K146:K148) -> 6269.0228 | L149: =SUM(L146:L148) -> 12961.486 | M149: =SUM(M146:M148) -> 20275.588 | N149: =SUM(N146:N148) -> 27388.738 | O149: =SUM(O146:O148) -> 34011.196
B152: Working Capital Schedule
B154: All figures in USD thousands unless stated | F154: =F$5 -> 44227 | G154: =G$5 -> 44591 | H154: =H$5 -> 44955 | I154: =I$5 -> 45319 | J154: =J$5 -> 45683 | K154: =K$5 -> 2026F | L154: =L$5 -> 2027F | M154: =M$5 -> 2028F | ... P154: =P$5 -> Term
B155: =$B$6 -> Model Running: Base Case Drivers
B157: Days in Period | F157: =F$8 -> 365 | G157: =G$8 -> 365 | H157: =H$8 -> 365 | I157: =I$8 -> 365 | J157: =J$8 -> 365 | K157: =K$8 -> 365 | L157: =L$8 -> 365 | M157: =M$8 -> 365 | ... P157: =P$8 -> 365
...

Sheet PBI - Export
B2: Table 1:
B3: Scenario | C3: WACC | D3: LT_Growth | E3: Terminal_Multiple | F3: Rev_CAGR | G3: LT_OpMargin | H3: FCF_Margin
B4: Bull | C4: 0.095 | D4: 0.04 | E4: 18 | F4: 0.3 | G4: 0.2 | H4: 0.18
B5: Base | C5: 0.1032 | D5: 0.03 | E5: 16 | F5: 0.25 | G5: 0.16 | H5: 0.13
B6: Bear | C6: 0.115 | D6: 0.02 | E6: 11 | F6: 0.18 | G6: 0.13 | H6: 0.1
B8: Table 2:
B9: Method | C9: Type
B10: Perpetuity | C10: DCF
B11: Exit Multiple | C11: DCF
B12: Relative | C12: MULT
B14: Table 3:
B15: Scenario | C15: Method | D15: ImpliedPrice
B16: Bull | C16: Perpetuity | D16: 279.74701
B17: Bull | C17: Exit Multiple | D17: 409.79326
B18: Bull | C18: Relative | D18: 55.704033
B19: Base | C19: Perpetuity | D19: 275.01776
B20: Base | C20: Exit Multiple | D20: 389.07761
B21: Base | C21: Relative | D21: 94.888311
B22: Bear | C22: Perpetuity | D22: 251.02158
B23: Bear | C23: Exit Multiple | D23: 338.97543
B24: Bear | C24: Relative | D24: 104.1755
B26: Table 4:
B27: Year | C27: Scenario | D27: Revenue | E27: EBIT | F27: FCF
B28: 2026 | C28: Base | D28: 207453 | E28: 38679 | F28: 41051
B29: 2027 | C29: Base | D29: 275813 | E29: 51079 | F29: 49163
B30: 2028 | C30: Base | D30: 328597 | E30: 55449 | F30: 53702
B31: 2029 | C31: Base | D31: 366767 | E31: 59288 | F31: 57601
B32: 2030 | C32: Base | D32: 395352 | E32: 64347 | F32: 61896
