Workbook

Sheet Cover
C4: Budget vs Actual Variance Analysis
C6: Table of Contents
C8: Budget_Annual
C9: Budget_QTR
C10: Variance_Annual

Sheet Budget_Annual
D1: NVIDIA CORPORATION (NASDAQGS:NVDA)
B3: Line item | D3: FY26 Budget
B5: Revenue | D5: 207452.85
B6: Graphics revenue | D6: 15734.4
B7: Compute & Networking revenue | D7: 191718.45
B8: Cost of goods sold (COGS) | D8: 56427.175
B9: Gross profit | D9: 151025.67
B10: Gross margin % | D10: 0.728
B11: SG&A | D11: 8713.0197
B12: SG&A % of revenue | D12: 0.042
B13: R&D | D13: 24894.342
B14: R&D % of revenue | D14: 0.12
B15: EBITDA | D15: 22819.814
B16: EBITDA margin % | D16: 0.11
... B24: Free Cash Flow | D24: 10306.407
B27: *Full‑year FY26 budget figures are based on NVIDIA’s forecasted FY26 financials, with forecast components (e.g. margins, FCF) adjusted using my own assumptions.

Sheet Budget_QTR
D1: NVIDIA CORPORATION (NASDAQGS:NVDA)
B3: Line item | D3: FY26 Budget | E3: Q1 % | F3: Q2 % | G3: Q3 % | H3: Q4 % | I3: Q1 2026 Budget | J3: Q2 2026 Budget | K3: Q3 2026 Budget | L3: Q4 2026 Budget | M3: Check
B5: Revenue | D5: =Budget_Annual!D5 -> 207452.85 | E5: 0.2 | F5: 0.23 | G5: 0.25 | H5: 0.32 | I5: =$D5*E5 -> 41490.57 | J5: =$D5*F5 -> 47714.155 | K5: =$D5*G5 -> 51863.212 | L5: =$D5*H5 -> 66384.912 | M5: =IF($D5=SUM($I5:$L5), "Yes", "No") -> Yes
B6: Graphics revenue | D6: =Budget_Annual!D6 -> 15734.4 | E6: 0.2 | F6: 0.23 | G6: 0.25 | H6: 0.32 | I6: =$D6*E6 -> 3146.88 | J6: =$D6*F6 -> 3618.912 | K6: =$D6*G6 -> 3933.6 | L6: =$D6*H6 -> 5035.008 | M6: =IF($D6=SUM($I6:$L6), "Yes", "No") -> Yes
B7: Compute & Networking revenue | D7: =Budget_Annual!D7 -> 191718.45 | E7: 0.2 | F7: 0.23 | G7: 0.25 | H7: 0.32 | I7: =$D7*E7 -> 38343.69 | J7: =$D7*F7 -> 44095.243 | K7: =$D7*G7 -> 47929.612 | L7: =$D7*H7 -> 61349.904 | M7: =IF($D7=SUM($I7:$L7), "Yes", "No") -> Yes
B8: Cost of goods sold (COGS) | D8: =Budget_Annual!D8 -> 56427.175 | E8: 0.2 | F8: 0.23 | G8: 0.25 | H8: 0.32 | I8: =$D8*E8 -> 11285.435 | J8: =$D8*F8 -> 12978.25 | K8: =$D8*G8 -> 14106.794 | L8: =$D8*H8 -> 18056.696 | M8: =IF($D8=SUM($I8:$L8), "Yes", "No") -> Yes
B9: Gross profit | D9: =Budget_Annual!D9 -> 151025.67 | E9: 0.2 | F9: 0.23 | G9: 0.25 | H9: 0.32 | I9: =$D9*E9 -> 30205.135 | J9: =$D9*F9 -> 34735.905 | K9: =$D9*G9 -> 37756.419 | L9: =$D9*H9 -> 48328.216 | M9: =IF($D9=SUM($I9:$L9), "Yes", "No") -> Yes
B10: SG&A | D10: =Budget_Annual!D11 -> 8713.0197 | E10: 0.2 | F10: 0.23 | G10: 0.25 | H10: 0.32 | I10: =$D10*E10 -> 1742.6039 | J10: =$D10*F10 -> 2003.9945 | K10: =$D10*G10 -> 2178.2549 | L10: =$D10*H10 -> 2788.1663 | M10: =IF($D10=SUM($I10:$L10), "Yes", "No") -> Yes
B11: R&D | D11: =Budget_Annual!D13 -> 24894.342 | E11: 0.2 | F11: 0.23 | G11: 0.25 | H11: 0.32 | I11: =$D11*E11 -> 4978.8684 | J11: =$D11*F11 -> 5725.6987 | K11: =$D11*G11 -> 6223.5855 | L11: =$D11*H11 -> 7966.1894 | M11: =IF($D11=SUM($I11:$L11), "Yes", "No") -> Yes
B12: EBIT | D12: =Budget_Annual!D18 -> 21007.045 | E12: 0.2 | F12: 0.23 | G12: 0.25 | H12: 0.32 | I12: =$D12*E12 -> 4201.4089 | J12: =$D12*F12 -> 4831.6203 | K12: =$D12*G12 -> 5251.7611 | L12: =$D12*H12 -> 6722.2543 | M12: =IF($D12=SUM($I12:$L12), "Yes", "No") -> Yes
B13: Net Income | D13: =Budget_Annual!D22 -> 17655.079 | E13: 0.2 | F13: 0.23 | G13: 0.25 | H13: 0.32 | I13: =$D13*E13 -> 3531.0158 | J13: =$D13*F13 -> 4060.6682 | K13: =$D13*G13 -> 4413.7698 | L13: =$D13*H13 -> 5649.6253 | M13: =IF($D13=SUM($I13:$L13), "Yes", "No") -> Yes
B14: Capex | D14: =Budget_Annual!D23 -> 5601.2269 | E14: 0.2 | F14: 0.23 | G14: 0.25 | H14: 0.32 | I14: =$D14*E14 -> 1120.2454 | J14: =$D14*F14 -> 1288.2822 | K14: =$D14*G14 -> 1400.3067 | L14: =$D14*H14 -> 1792.3926 | M14: =IF($D14=SUM($I14:$L14), "Yes", "No") -> Yes
B15: Free Cash Flow | D15: =Budget_Annual!D24 -> 10306.407 | E15: 0.2 | F15: 0.23 | G15: 0.25 | H15: 0.32 | I15: =$D15*E15 -> 2061.2815 | J15: =$D15*F15 -> 2370.4737 | K15: =$D15*G15 -> 2576.6018 | L15: =$D15*H15 -> 3298.0503 | M15: =IF($D15=SUM($I15:$L15), "Yes", "No") -> Yes
B18: *Notes: Quarterly % splits (20/23/25/32) are a modelling assumption based on NVIDIA’s typical pattern of lower Q1 and stronger Q3–Q4, and are applied uniformly across line items to phase the annual FY26 budget into quarters.
B19: *In practice, individual line items may differ slightly by quarter, but this approach is sufficient for high‑level planning.

Sheet Variance_Annual
D1: NVIDIA CORPORATION (NASDAQGS:NVDA)
B3: Line item | E3: FY26 Budget | F3: 2026 Actual | G3: Var $ | H3: Var % | I3: F/U
B5: Revenue | E5: =Budget_QTR!D5 -> 207452.85 | F5: 215938 | G5: =F5-E5 -> 8485.15 | H5: =IF(E5=0,"",(F5-E5)/E5) -> 0.040901583 | I5: =IF(OR(TRIM(B5)="Revenue",TRIM(B5)="Graphics revenue",TRIM(B5)="Compute & Networking revenue",TRIM(B5)="Gross profit",TRIM(B5)="EBITDA",TRIM(B5)="EBIT",TRIM(B5)="Net Income",TRIM(B5)="Free Cash Flow"),IF(H5>0,"Favourable","Unfavourable"),IF(H5<0,"Favourable","Unfavourable")) -> Favourable
B6: Graphics revenue | E6: =Budget_QTR!D6 -> 15734.4 | F6: 22459 | G6: =F6-E6 -> 6724.6 | H6: =IF(E6=0,"",(F6-E6)/E6) -> 0.42738204 | I6: =IF(OR(TRIM(B6)="Revenue",TRIM(B6)="Graphics revenue",TRIM(B6)="Compute & Networking revenue",TRIM(B6)="Gross profit",TRIM(B6)="EBITDA",TRIM(B6)="EBIT",TRIM(B6)="Net Income",TRIM(B6)="Free Cash Flow"),IF(H6>0,"Favourable","Unfavourable"),IF(H6<0,"Favourable","Unfavourable")) -> Favourable
B7: Compute & Networking revenue | E7: =Budget_QTR!D7 -> 191718.45 | F7: 193479 | G7: =F7-E7 -> 1760.55 | H7: =IF(E7=0,"",(F7-E7)/E7) -> 0.0091829973 | I7: =IF(OR(TRIM(B7)="Revenue",TRIM(B7)="Graphics revenue",TRIM(B7)="Compute & Networking revenue",TRIM(B7)="Gross profit",TRIM(B7)="EBITDA",TRIM(B7)="EBIT",TRIM(B7)="Net Income",TRIM(B7)="Free Cash Flow"),IF(H7>0,"Favourable","Unfavourable"),IF(H7<0,"Favourable","Unfavourable")) -> Favourable
B8: Cost of goods sold (COGS) | E8: =Budget_QTR!D8 -> 56427.175 | F8: 62475 | G8: =F8-E8 -> 6047.8248 | H8: =IF(E8=0,"",(F8-E8)/E8) -> 0.10717929 | I8: =IF(OR(TRIM(B8)="Revenue",TRIM(B8)="Graphics revenue",TRIM(B8)="Compute & Networking revenue",TRIM(B8)="Gross profit",TRIM(B8)="EBITDA",TRIM(B8)="EBIT",TRIM(B8)="Net Income",TRIM(B8)="Free Cash Flow"),IF(H8>0,"Favourable","Unfavourable"),IF(H8<0,"Favourable","Unfavourable")) -> Unfavourable
B9: Gross profit | E9: =Budget_QTR!D9 -> 151025.67 | F9: 153463 | G9: =F9-E9 -> 2437.3252 | H9: =IF(E9=0,"",(F9-E9)/E9) -> 0.016138482 | I9: =IF(OR(TRIM(B9)="Revenue",TRIM(B9)="Graphics revenue",TRIM(B9)="Compute & Networking revenue",TRIM(B9)="Gross profit",TRIM(B9)="EBITDA",TRIM(B9)="EBIT",TRIM(B9)="Net Income",TRIM(B9)="Free Cash Flow"),IF(H9>0,"Favourable","Unfavourable"),IF(H9<0,"Favourable","Unfavourable")) -> Favourable
B10: SG&A | E10: =Budget_QTR!D10 -> 8713.0197 | F10: 4579 | G10: =F10-E10 -> -4134.0197 | H10: =IF(E10=0,"",(F10-E10)/E10) -> -0.47446463 | I10: =IF(OR(TRIM(B10)="Revenue",TRIM(B10)="Graphics revenue",TRIM(B10)="Compute & Networking revenue",TRIM(B10)="Gross profit",TRIM(B10)="EBITDA",TRIM(B10)="EBIT",TRIM(B10)="Net Income",TRIM(B10)="Free Cash Flow"),IF(H10>0,"Favourable","Unfavourable"),IF(H10<0,"Favourable","Unfavourable")) -> Favourable
B11: R&D | E11: =Budget_QTR!D11 -> 24894.342 | F11: 18497 | G11: =F11-E11 -> -6397.342 | H11: =IF(E11=0,"",(F11-E11)/E11) -> -0.25697976 | I11: =IF(OR(TRIM(B11)="Revenue",TRIM(B11)="Graphics revenue",TRIM(B11)="Compute & Networking revenue",TRIM(B11)="Gross profit",TRIM(B11)="EBITDA",TRIM(B11)="EBIT",TRIM(B11)="Net Income",TRIM(B11)="Free Cash Flow"),IF(H11>0,"Favourable","Unfavourable"),IF(H11<0,"Favourable","Unfavourable")) -> Favourable
B12: EBITDA | E12: =Budget_Annual!D15 -> 22819.814 | F12: 38446 | G12: =F12-E12 -> 15626.186 | H12: =IF(E12=0,"",(F12-E12)/E12) -> 0.68476399 | I12: =IF(OR(TRIM(B12)="Revenue",TRIM(B12)="Graphics revenue",TRIM(B12)="Compute & Networking revenue",TRIM(B12)="Gross profit",TRIM(B12)="EBITDA",TRIM(B12)="EBIT",TRIM(B12)="Net Income",TRIM(B12)="Free Cash Flow"),IF(H12>0,"Favourable","Unfavourable"),IF(H12<0,"Favourable","Unfavourable")) -> Favourable
B13: EBIT | E13: =Budget_QTR!D12 -> 21007.045 | F13: 141450 | G13: =F13-E13 -> 120442.96 | H13: =IF(E13=0,"",(F13-E13)/E13) -> 5.7334555 | I13: =IF(OR(TRIM(B13)="Revenue",TRIM(B13)="Graphics revenue",TRIM(B13)="Compute & Networking revenue",TRIM(B13)="Gross profit",TRIM(B13)="EBITDA",TRIM(B13)="EBIT",TRIM(B13)="Net Income",TRIM(B13)="Free Cash Flow"),IF(H13>0,"Favourable","Unfavourable"),IF(H13<0,"Favourable","Unfavourable")) -> Favourable
B14: Net Income | E14: =Budget_QTR!D13 -> 17655.079 | F14: 120067 | G14: =F14-E14 -> 102411.92 | H14: =IF(E14=0,"",(F14-E14)/E14) -> 5.8007059 | I14: =IF(OR(TRIM(B14)="Revenue",TRIM(B14)="Graphics revenue",TRIM(B14)="Compute & Networking revenue",TRIM(B14)="Gross profit",TRIM(B14)="EBITDA",TRIM(B14)="EBIT",TRIM(B14)="Net Income",TRIM(B14)="Free Cash Flow"),IF(H14>0,"Favourable","Unfavourable"),IF(H14<0,"Favourable","Unfavourable")) -> Favourable
B15: Capex | E15: =Budget_QTR!D14 -> 5601.2269 | F15: 6100 | G15: =F15-E15 -> 498.77305 | H15: =IF(E15=0,"",(F15-E15)/E15) -> 0.089047106 | I15: =IF(OR(TRIM(B15)="Revenue",TRIM(B15)="Graphics revenue",TRIM(B15)="Compute & Networking revenue",TRIM(B15)="Gross profit",TRIM(B15)="EBITDA",TRIM(B15)="EBIT",TRIM(B15)="Net Income",TRIM(B15)="Free Cash Flow"),IF(H15>0,"Favourable","Unfavourable"),IF(H15<0,"Favourable","Unfavourable")) -> Unfavourable
B16: Free Cash Flow | E16: =Budget_QTR!D15 -> 10306.407 | F16: 77035 | G16: =F16-E16 -> 66728.593 | H16: =IF(E16=0,"",(F16-E16)/E16) -> 6.4744766 | I16: =IF(OR(TRIM(B16)="Revenue",TRIM(B16)="Graphics revenue",TRIM(B16)="Compute & Networking revenue",TRIM(B16)="Gross profit",TRIM(B16)="EBITDA",TRIM(B16)="EBIT",TRIM(B16)="Net Income",TRIM(B16)="Free Cash Flow"),IF(H16>0,"Favourable","Unfavourable"),IF(H16<0,"Favourable","Unfavourable")) -> Favourable
B19: *Actual FY26 figures are taken from NVIDIA’s FY2026 Q4. Budget figures are based on the FY26 budget in this model.
B20: *F/U Logic: Revenue/profit beats = Favourable. Cost overruns = Unfavourable. Single formula with TRIM() for consistent line item matching.
